{
    "FldHeader": {
        "NumBlockDataRecords": 0,
        "NumMisc3dObjectRecords": 0,
        "NumMiscFlatObjectRecords": 0,
        "BlockPositions": null,
        "BuildingDataList": [],
        "BlockDataSizes": null,
        "GroundData": {},
        "AutoMapData": null,
        "Name": null,
        "OtherNames": null
    },
    "SubRecords": [],
    "Misc3dObjectRecords": [
        {
            "ModelId": "41222",
            "ModelIdNum": 41222,
            "ObjectType": 0,
            "XPos": 1499,
            "YPos": -25,
            "ZPos": -1663,
            "XScale": 1.0,
            "YScale": 1.0,
            "ZScale": 1.0,
            "XRotation": 0,
            "YRotation": 0,
            "ZRotation": 0
        },
        {
            "ModelId": "53124",
            "ModelIdNum": 53124,
            "ObjectType": 0,
            "XPos": 1382,
            "YPos": 4,
            "ZPos": -1319,
            "XScale": 1.0,
            "YScale": 1.0,
            "ZScale": 1.0,
            "XRotation": 0,
            "YRotation": -1365,
            "ZRotation": 0
        },
        {
            "ModelId": "53103",
            "ModelIdNum": 53103,
            "ObjectType": 0,
            "XPos": 1171,
            "YPos": -3,
            "ZPos": -1538,
            "XScale": 1.0,
            "YScale": 1.0,
            "ZScale": 1.0,
            "XRotation": 0,
            "YRotation": -1195,
            "ZRotation": 0
        },
        {
            "ModelId": "53102",
            "ModelIdNum": 53102,
            "ObjectType": 0,
            "XPos": 1830,
            "YPos": -3,
            "ZPos": -1628,
            "XScale": 1.0,
            "YScale": 1.0,
            "ZScale": 1.0,
            "XRotation": 0,
            "YRotation": 0,
            "ZRotation": 0
        },
        {
            "ModelId": "53124",
            "ModelIdNum": 53124,
            "ObjectType": 0,
            "XPos": 1194,
            "YPos": 3,
            "ZPos": -1858,
            "XScale": 1.0,
            "YScale": 1.0,
            "ZScale": 1.0,
            "XRotation": 0,
            "YRotation": -853,
            "ZRotation": 0
        },
        {
            "ModelId": "53100",
            "ModelIdNum": 53100,
            "ObjectType": 0,
            "XPos": 1677,
            "YPos": -3,
            "ZPos": -1340,
            "XScale": 1.0,
            "YScale": 1.0,
            "ZScale": 1.0,
            "XRotation": 0,
            "YRotation": -1707,
            "ZRotation": 0
        },
        {
            "ModelId": "53122",
            "ModelIdNum": 53122,
            "ObjectType": 0,
            "XPos": 1436,
            "YPos": 3,
            "ZPos": -1997,
            "XScale": 1.0,
            "YScale": 1.0,
            "ZScale": 1.0,
            "XRotation": 0,
            "YRotation": -597,
            "ZRotation": 0
        },
        {
            "ModelId": "41214",
            "ModelIdNum": 41214,
            "ObjectType": 0,
            "XPos": 1649,
            "YPos": -33,
            "ZPos": -1574,
            "XScale": 1.0,
            "YScale": 1.0,
            "ZScale": 1.0,
            "XRotation": 0,
            "YRotation": -1917,
            "ZRotation": 0
        },
        {
            "ModelId": "53108",
            "ModelIdNum": 53108,
            "ObjectType": 0,
            "XPos": 1710,
            "YPos": -3,
            "ZPos": -1892,
            "XScale": 1.0,
            "YScale": 1.0,
            "ZScale": 1.0,
            "XRotation": 0,
            "YRotation": -255,
            "ZRotation": 0
        }
    ],
    "MiscFlatObjectRecords": [
        {
            "Position": 5315,
            "XPos": 1825,
            "YPos": -47,
            "ZPos": -1607,
            "TextureArchive": 1021,
            "TextureRecord": 3,
            "FactionID": 0,
            "Flags": 0
        },
        {
            "Position": 6929,
            "XPos": 1226,
            "YPos": -5,
            "ZPos": -1841,
            "TextureArchive": 184,
            "TextureRecord": 26,
            "FactionID": 584,
            "Flags": 0
        },
        {
            "Position": 7331,
            "XPos": 1721,
            "YPos": -47,
            "ZPos": -1860,
            "TextureArchive": 211,
            "TextureRecord": 31,
            "FactionID": 0,
            "Flags": 0
        },
        {
            "Position": 9543,
            "XPos": 1620,
            "YPos": -5,
            "ZPos": -1867,
            "TextureArchive": 214,
            "TextureRecord": 5,
            "FactionID": 0,
            "Flags": 0
        },
        {
            "Position": 7604,
            "XPos": 1202,
            "YPos": -47,
            "ZPos": -1526,
            "TextureArchive": 213,
            "TextureRecord": 1,
            "FactionID": 0,
            "Flags": 0
        },
        {
            "Position": 9765,
            "XPos": 1175,
            "YPos": -47,
            "ZPos": -1569,
            "TextureArchive": 213,
            "TextureRecord": 0,
            "FactionID": 0,
            "Flags": 0
        },
        {
            "Position": 6493,
            "XPos": 1804,
            "YPos": -47,
            "ZPos": -1657,
            "TextureArchive": 1021,
            "TextureRecord": 3,
            "FactionID": 0,
            "Flags": 0
        },
        {
            "Position": 5250,
            "XPos": 1487,
            "YPos": -4,
            "ZPos": -1956,
            "TextureArchive": 201,
            "TextureRecord": 5,
            "FactionID": 0,
            "Flags": 0
        },
        {
            "Position": 6813,
            "XPos": 1674,
            "YPos": -47,
            "ZPos": -1908,
            "TextureArchive": 1021,
            "TextureRecord": 6,
            "FactionID": 0,
            "Flags": 0
        },
        {
            "Position": 5355,
            "XPos": 1185,
            "YPos": -47,
            "ZPos": -1521,
            "TextureArchive": 213,
            "TextureRecord": 1,
            "FactionID": 0,
            "Flags": 0
        },
        {
            "Position": 5748,
            "XPos": 1195,
            "YPos": -47,
            "ZPos": -1529,
            "TextureArchive": 213,
            "TextureRecord": 1,
            "FactionID": 0,
            "Flags": 0
        },
        {
            "Position": 8634,
            "XPos": 1210,
            "YPos": -47,
            "ZPos": -1517,
            "TextureArchive": 213,
            "TextureRecord": 1,
            "FactionID": 0,
            "Flags": 0
        },
        {
            "Position": 6631,
            "XPos": 1700,
            "YPos": -47,
            "ZPos": -1884,
            "TextureArchive": 1021,
            "TextureRecord": 7,
            "FactionID": 0,
            "Flags": 0
        },
        {
            "Position": 7318,
            "XPos": 1185,
            "YPos": -47,
            "ZPos": -1515,
            "TextureArchive": 213,
            "TextureRecord": 1,
            "FactionID": 0,
            "Flags": 0
        },
        {
            "Position": 8615,
            "XPos": 1821,
            "YPos": -47,
            "ZPos": -1649,
            "TextureArchive": 1021,
            "TextureRecord": 3,
            "FactionID": 0,
            "Flags": 0
        },
        {
            "Position": 5667,
            "XPos": 1207,
            "YPos": -47,
            "ZPos": -1505,
            "TextureArchive": 213,
            "TextureRecord": 1,
            "FactionID": 0,
            "Flags": 0
        },
        {
            "Position": 6292,
            "XPos": 1150,
            "YPos": -47,
            "ZPos": -1567,
            "TextureArchive": 213,
            "TextureRecord": 0,
            "FactionID": 0,
            "Flags": 0
        },
        {
            "Position": 6040,
            "XPos": 1169,
            "YPos": -47,
            "ZPos": -1574,
            "TextureArchive": 213,
            "TextureRecord": 0,
            "FactionID": 0,
            "Flags": 0
        },
        {
            "Position": 9557,
            "XPos": 1295,
            "YPos": -4,
            "ZPos": -1735,
            "TextureArchive": 1010,
            "TextureRecord": 17,
            "FactionID": 0,
            "Flags": 0
        },
        {
            "Position": 6405,
            "XPos": 1287,
            "YPos": -4,
            "ZPos": -1826,
            "TextureArchive": 1010,
            "TextureRecord": 15,
            "FactionID": 0,
            "Flags": 0
        },
        {
            "Position": 6467,
            "XPos": 1158,
            "YPos": -47,
            "ZPos": -1570,
            "TextureArchive": 213,
            "TextureRecord": 0,
            "FactionID": 0,
            "Flags": 0
        },
        {
            "Position": 9310,
            "XPos": 1716,
            "YPos": -47,
            "ZPos": -1883,
            "TextureArchive": 1021,
            "TextureRecord": 7,
            "FactionID": 0,
            "Flags": 0
        },
        {
            "Position": 9440,
            "XPos": 1174,
            "YPos": -47,
            "ZPos": -1578,
            "TextureArchive": 213,
            "TextureRecord": 0,
            "FactionID": 0,
            "Flags": 0
        },
        {
            "Position": 7225,
            "XPos": 1199,
            "YPos": -47,
            "ZPos": -1515,
            "TextureArchive": 213,
            "TextureRecord": 1,
            "FactionID": 0,
            "Flags": 0
        },
        {
            "Position": 8534,
            "XPos": 1392,
            "YPos": -4,
            "ZPos": -1325,
            "TextureArchive": 1024,
            "TextureRecord": 1,
            "FactionID": 0,
            "Flags": 0
        },
        {
            "Position": 8111,
            "XPos": 1701,
            "YPos": -47,
            "ZPos": -1869,
            "TextureArchive": 1021,
            "TextureRecord": 7,
            "FactionID": 0,
            "Flags": 0
        },
        {
            "Position": 6237,
            "XPos": 1189,
            "YPos": -47,
            "ZPos": -1531,
            "TextureArchive": 213,
            "TextureRecord": 1,
            "FactionID": 0,
            "Flags": 0
        },
        {
            "Position": 6076,
            "XPos": 1457,
            "YPos": -4,
            "ZPos": -1327,
            "TextureArchive": 1024,
            "TextureRecord": 2,
            "FactionID": 0,
            "Flags": 0
        },
        {
            "Position": 7437,
            "XPos": 1191,
            "YPos": -47,
            "ZPos": -1526,
            "TextureArchive": 213,
            "TextureRecord": 1,
            "FactionID": 0,
            "Flags": 0
        },
        {
            "Position": 8790,
            "XPos": 1175,
            "YPos": -47,
            "ZPos": -1519,
            "TextureArchive": 213,
            "TextureRecord": 1,
            "FactionID": 0,
            "Flags": 0
        },
        {
            "Position": 9352,
            "XPos": 1821,
            "YPos": -47,
            "ZPos": -1667,
            "TextureArchive": 1021,
            "TextureRecord": 3,
            "FactionID": 0,
            "Flags": 0
        },
        {
            "Position": 8076,
            "XPos": 1814,
            "YPos": -47,
            "ZPos": -1612,
            "TextureArchive": 1021,
            "TextureRecord": 3,
            "FactionID": 0,
            "Flags": 0
        },
        {
            "Position": 6630,
            "XPos": 1232,
            "YPos": -4,
            "ZPos": -1789,
            "TextureArchive": 1010,
            "TextureRecord": 16,
            "FactionID": 0,
            "Flags": 0
        },
        {
            "Position": 7571,
            "XPos": 1183,
            "YPos": -47,
            "ZPos": -1535,
            "TextureArchive": 213,
            "TextureRecord": 1,
            "FactionID": 0,
            "Flags": 0
        },
        {
            "Position": 6965,
            "XPos": 1203,
            "YPos": -47,
            "ZPos": -1514,
            "TextureArchive": 213,
            "TextureRecord": 1,
            "FactionID": 0,
            "Flags": 0
        },
        {
            "Position": 6200,
            "XPos": 1815,
            "YPos": -47,
            "ZPos": -1591,
            "TextureArchive": 1021,
            "TextureRecord": 3,
            "FactionID": 0,
            "Flags": 0
        },
        {
            "Position": 9261,
            "XPos": 1307,
            "YPos": -4,
            "ZPos": -1404,
            "TextureArchive": 205,
            "TextureRecord": 30,
            "FactionID": 0,
            "Flags": 0
        },
        {
            "Position": 7235,
            "XPos": 1199,
            "YPos": -47,
            "ZPos": -1520,
            "TextureArchive": 213,
            "TextureRecord": 1,
            "FactionID": 0,
            "Flags": 0
        },
        {
            "Position": 6195,
            "XPos": 1165,
            "YPos": -47,
            "ZPos": -1564,
            "TextureArchive": 213,
            "TextureRecord": 0,
            "FactionID": 0,
            "Flags": 0
        },
        {
            "Position": 8626,
            "XPos": 1191,
            "YPos": -47,
            "ZPos": -1521,
            "TextureArchive": 213,
            "TextureRecord": 1,
            "FactionID": 0,
            "Flags": 0
        },
        {
            "Position": 7885,
            "XPos": 1183,
            "YPos": -47,
            "ZPos": -1577,
            "TextureArchive": 213,
            "TextureRecord": 0,
            "FactionID": 0,
            "Flags": 0
        },
        {
            "Position": 8668,
            "XPos": 1213,
            "YPos": -47,
            "ZPos": -1514,
            "TextureArchive": 213,
            "TextureRecord": 1,
            "FactionID": 0,
            "Flags": 0
        },
        {
            "Position": 5144,
            "XPos": 1197,
            "YPos": -47,
            "ZPos": -1521,
            "TextureArchive": 213,
            "TextureRecord": 1,
            "FactionID": 0,
            "Flags": 0
        },
        {
            "Position": 7410,
            "XPos": 1185,
            "YPos": -47,
            "ZPos": -1537,
            "TextureArchive": 213,
            "TextureRecord": 1,
            "FactionID": 0,
            "Flags": 0
        },
        {
            "Position": 8925,
            "XPos": 1195,
            "YPos": -47,
            "ZPos": -1536,
            "TextureArchive": 213,
            "TextureRecord": 1,
            "FactionID": 0,
            "Flags": 0
        },
        {
            "Position": 7875,
            "XPos": 1683,
            "YPos": -47,
            "ZPos": -1370,
            "TextureArchive": 211,
            "TextureRecord": 40,
            "FactionID": 0,
            "Flags": 0
        },
        {
            "Position": 8335,
            "XPos": 1172,
            "YPos": -47,
            "ZPos": -1534,
            "TextureArchive": 213,
            "TextureRecord": 1,
            "FactionID": 0,
            "Flags": 0
        },
        {
            "Position": 9716,
            "XPos": 1171,
            "YPos": -47,
            "ZPos": -1546,
            "TextureArchive": 213,
            "TextureRecord": 1,
            "FactionID": 0,
            "Flags": 0
        },
        {
            "Position": 8563,
            "XPos": 1644,
            "YPos": -47,
            "ZPos": -1339,
            "TextureArchive": 214,
            "TextureRecord": 13,
            "FactionID": 0,
            "Flags": 0
        },
        {
            "Position": 8749,
            "XPos": 1194,
            "YPos": -47,
            "ZPos": -1510,
            "TextureArchive": 213,
            "TextureRecord": 1,
            "FactionID": 0,
            "Flags": 0
        },
        {
            "Position": 5304,
            "XPos": 1148,
            "YPos": -47,
            "ZPos": -1576,
            "TextureArchive": 213,
            "TextureRecord": 0,
            "FactionID": 0,
            "Flags": 0
        },
        {
            "Position": 7218,
            "XPos": 1198,
            "YPos": -47,
            "ZPos": -1501,
            "TextureArchive": 213,
            "TextureRecord": 1,
            "FactionID": 0,
            "Flags": 0
        },
        {
            "Position": 5919,
            "XPos": 1199,
            "YPos": -47,
            "ZPos": -1539,
            "TextureArchive": 213,
            "TextureRecord": 1,
            "FactionID": 0,
            "Flags": 0
        },
        {
            "Position": 8580,
            "XPos": 1162,
            "YPos": -47,
            "ZPos": -1579,
            "TextureArchive": 213,
            "TextureRecord": 0,
            "FactionID": 0,
            "Flags": 0
        },
        {
            "Position": 8555,
            "XPos": 1673,
            "YPos": -5,
            "ZPos": -1862,
            "TextureArchive": 182,
            "TextureRecord": 12,
            "FactionID": 584,
            "Flags": 0
        },
        {
            "Position": 8553,
            "XPos": 1738,
            "YPos": -47,
            "ZPos": -1861,
            "TextureArchive": 1021,
            "TextureRecord": 8,
            "FactionID": 0,
            "Flags": 0
        },
        {
            "Position": 8650,
            "XPos": 1432,
            "YPos": -5,
            "ZPos": -1921,
            "TextureArchive": 182,
            "TextureRecord": 18,
            "FactionID": 584,
            "Flags": 0
        },
        {
            "Position": 9249,
            "XPos": 1193,
            "YPos": -47,
            "ZPos": -1507,
            "TextureArchive": 213,
            "TextureRecord": 1,
            "FactionID": 0,
            "Flags": 0
        },
        {
            "Position": 6313,
            "XPos": 1807,
            "YPos": -47,
            "ZPos": -1600,
            "TextureArchive": 1021,
            "TextureRecord": 3,
            "FactionID": 0,
            "Flags": 0
        },
        {
            "Position": 5246,
            "XPos": 1183,
            "YPos": -47,
            "ZPos": -1529,
            "TextureArchive": 213,
            "TextureRecord": 1,
            "FactionID": 0,
            "Flags": 0
        },
        {
            "Position": 6016,
            "XPos": 1180,
            "YPos": -47,
            "ZPos": -1529,
            "TextureArchive": 213,
            "TextureRecord": 1,
            "FactionID": 0,
            "Flags": 0
        },
        {
            "Position": 6301,
            "XPos": 1201,
            "YPos": -47,
            "ZPos": -1508,
            "TextureArchive": 213,
            "TextureRecord": 1,
            "FactionID": 0,
            "Flags": 0
        },
        {
            "Position": 5950,
            "XPos": 1368,
            "YPos": -4,
            "ZPos": -1498,
            "TextureArchive": 201,
            "TextureRecord": 5,
            "FactionID": 0,
            "Flags": 0
        },
        {
            "Position": 8719,
            "XPos": 1222,
            "YPos": -5,
            "ZPos": -1562,
            "TextureArchive": 184,
            "TextureRecord": 28,
            "FactionID": 584,
            "Flags": 0
        },
        {
            "Position": 6990,
            "XPos": 1333,
            "YPos": -4,
            "ZPos": -1883,
            "TextureArchive": 214,
            "TextureRecord": 14,
            "FactionID": 0,
            "Flags": 0
        },
        {
            "Position": 6217,
            "XPos": 1195,
            "YPos": -47,
            "ZPos": -1546,
            "TextureArchive": 213,
            "TextureRecord": 1,
            "FactionID": 0,
            "Flags": 0
        },
        {
            "Position": 7919,
            "XPos": 1180,
            "YPos": -47,
            "ZPos": -1524,
            "TextureArchive": 213,
            "TextureRecord": 1,
            "FactionID": 0,
            "Flags": 0
        },
        {
            "Position": 6440,
            "XPos": 1183,
            "YPos": -47,
            "ZPos": -1553,
            "TextureArchive": 213,
            "TextureRecord": 1,
            "FactionID": 0,
            "Flags": 0
        },
        {
            "Position": 5269,
            "XPos": 1157,
            "YPos": -47,
            "ZPos": -1555,
            "TextureArchive": 213,
            "TextureRecord": 0,
            "FactionID": 0,
            "Flags": 0
        },
        {
            "Position": 8860,
            "XPos": 1825,
            "YPos": -47,
            "ZPos": -1628,
            "TextureArchive": 1021,
            "TextureRecord": 3,
            "FactionID": 0,
            "Flags": 0
        },
        {
            "Position": 5319,
            "XPos": 1775,
            "YPos": -5,
            "ZPos": -1630,
            "TextureArchive": 184,
            "TextureRecord": 24,
            "FactionID": 584,
            "Flags": 0
        },
        {
            "Position": 5749,
            "XPos": 1411,
            "YPos": -4,
            "ZPos": -1311,
            "TextureArchive": 1024,
            "TextureRecord": 2,
            "FactionID": 0,
            "Flags": 0
        },
        {
            "Position": 7158,
            "XPos": 1641,
            "YPos": -4,
            "ZPos": -1390,
            "TextureArchive": 184,
            "TextureRecord": 16,
            "FactionID": 584,
            "Flags": 0
        },
        {
            "Position": 5657,
            "XPos": 1804,
            "YPos": -47,
            "ZPos": -1622,
            "TextureArchive": 1021,
            "TextureRecord": 3,
            "FactionID": 0,
            "Flags": 0
        },
        {
            "Position": 7140,
            "XPos": 1187,
            "YPos": -47,
            "ZPos": -1545,
            "TextureArchive": 213,
            "TextureRecord": 1,
            "FactionID": 0,
            "Flags": 0
        },
        {
            "Position": 7084,
            "XPos": 1702,
            "YPos": -47,
            "ZPos": -1362,
            "TextureArchive": 211,
            "TextureRecord": 40,
            "FactionID": 0,
            "Flags": 0
        },
        {
            "Position": 6512,
            "XPos": 1204,
            "YPos": -47,
            "ZPos": -1510,
            "TextureArchive": 213,
            "TextureRecord": 1,
            "FactionID": 0,
            "Flags": 0
        },
        {
            "Position": 7001,
            "XPos": 1218,
            "YPos": -47,
            "ZPos": -1511,
            "TextureArchive": 213,
            "TextureRecord": 1,
            "FactionID": 0,
            "Flags": 0
        },
        {
            "Position": 9101,
            "XPos": 1746,
            "YPos": -4,
            "ZPos": -1455,
            "TextureArchive": 205,
            "TextureRecord": 0,
            "FactionID": 0,
            "Flags": 0
        },
        {
            "Position": 8973,
            "XPos": 1191,
            "YPos": -47,
            "ZPos": -1521,
            "TextureArchive": 213,
            "TextureRecord": 1,
            "FactionID": 0,
            "Flags": 0
        },
        {
            "Position": 6122,
            "XPos": 1183,
            "YPos": -47,
            "ZPos": -1513,
            "TextureArchive": 213,
            "TextureRecord": 1,
            "FactionID": 0,
            "Flags": 0
        },
        {
            "Position": 7540,
            "XPos": 1420,
            "YPos": -5,
            "ZPos": -1362,
            "TextureArchive": 184,
            "TextureRecord": 25,
            "FactionID": 584,
            "Flags": 0
        },
        {
            "Position": 9033,
            "XPos": 1810,
            "YPos": -47,
            "ZPos": -1640,
            "TextureArchive": 1021,
            "TextureRecord": 3,
            "FactionID": 0,
            "Flags": 0
        },
        {
            "Position": 9964,
            "XPos": 1340,
            "YPos": -4,
            "ZPos": -1346,
            "TextureArchive": 1024,
            "TextureRecord": 0,
            "FactionID": 0,
            "Flags": 0
        },
        {
            "Position": 6144,
            "XPos": 1183,
            "YPos": -47,
            "ZPos": -1563,
            "TextureArchive": 213,
            "TextureRecord": 0,
            "FactionID": 0,
            "Flags": 0
        },
        {
            "Position": 9832,
            "XPos": 1418,
            "YPos": -4,
            "ZPos": -1967,
            "TextureArchive": 201,
            "TextureRecord": 6,
            "FactionID": 0,
            "Flags": 0
        },
        {
            "Position": 9495,
            "XPos": 1171,
            "YPos": -47,
            "ZPos": -1585,
            "TextureArchive": 213,
            "TextureRecord": 0,
            "FactionID": 0,
            "Flags": 0
        },
        {
            "Position": 5755,
            "XPos": 1182,
            "YPos": -47,
            "ZPos": -1543,
            "TextureArchive": 213,
            "TextureRecord": 1,
            "FactionID": 0,
            "Flags": 0
        },
        {
            "Position": 9015,
            "XPos": 1183,
            "YPos": -47,
            "ZPos": -1531,
            "TextureArchive": 213,
            "TextureRecord": 1,
            "FactionID": 0,
            "Flags": 0
        },
        {
            "Position": 9412,
            "XPos": 1678,
            "YPos": -47,
            "ZPos": -1349,
            "TextureArchive": 211,
            "TextureRecord": 40,
            "FactionID": 0,
            "Flags": 0
        }
    ]
}