{
    "FldHeader": {
        "NumBlockDataRecords": 0,
        "NumMisc3dObjectRecords": 0,
        "NumMiscFlatObjectRecords": 0,
        "BlockPositions": null,
        "BuildingDataList": [],
        "BlockDataSizes": null,
        "GroundData": {},
        "AutoMapData": null,
        "Name": null,
        "OtherNames": null
    },
    "SubRecords": [],
    "Misc3dObjectRecords": [
        {
            "ModelId": "43307",
            "ModelIdNum": 43307,
            "ObjectType": 0,
            "XPos": 3905,
            "YPos": -15,
            "ZPos": -1103,
            "XScale": 1.0,
            "YScale": 1.0,
            "ZScale": 1.0,
            "XRotation": 0,
            "YRotation": -1541,
            "ZRotation": 0
        },
        {
            "ModelId": "45077",
            "ModelIdNum": 45077,
            "ObjectType": 0,
            "XPos": 820,
            "YPos": -380,
            "ZPos": -1839,
            "XScale": 1.0,
            "YScale": 1.0,
            "ZScale": 1.0,
            "XRotation": 0,
            "YRotation": 0,
            "ZRotation": 0
        },
        {
            "ModelId": "21107",
            "ModelIdNum": 21107,
            "ObjectType": 0,
            "XPos": 1866,
            "YPos": 1,
            "ZPos": -1984,
            "XScale": 1.0,
            "YScale": 1.0,
            "ZScale": 1.0,
            "XRotation": 0,
            "YRotation": -512,
            "ZRotation": 0
        },
        {
            "ModelId": "45095",
            "ModelIdNum": 45095,
            "ObjectType": 0,
            "XPos": 3392,
            "YPos": 0,
            "ZPos": -2736,
            "XScale": 1.0,
            "YScale": 1.0,
            "ZScale": 1.0,
            "XRotation": 0,
            "YRotation": -1393,
            "ZRotation": 0
        },
        {
            "ModelId": "40014",
            "ModelIdNum": 40014,
            "ObjectType": 0,
            "XPos": 3888,
            "YPos": 1,
            "ZPos": -1509,
            "XScale": 1.0,
            "YScale": 1.0,
            "ZScale": 1.0,
            "XRotation": 0,
            "YRotation": 0,
            "ZRotation": 0
        },
        {
            "ModelId": "43307",
            "ModelIdNum": 43307,
            "ObjectType": 0,
            "XPos": 3904,
            "YPos": -15,
            "ZPos": -1336,
            "XScale": 1.0,
            "YScale": 1.0,
            "ZScale": 1.0,
            "XRotation": 0,
            "YRotation": -1541,
            "ZRotation": 0
        },
        {
            "ModelId": "21107",
            "ModelIdNum": 21107,
            "ObjectType": 0,
            "XPos": 705,
            "YPos": 1,
            "ZPos": -2214,
            "XScale": 1.0,
            "YScale": 1.0,
            "ZScale": 1.0,
            "XRotation": 0,
            "YRotation": -1507,
            "ZRotation": 0
        },
        {
            "ModelId": "21107",
            "ModelIdNum": 21107,
            "ObjectType": 0,
            "XPos": 1750,
            "YPos": 1,
            "ZPos": -2218,
            "XScale": 1.0,
            "YScale": 1.0,
            "ZScale": 1.0,
            "XRotation": 0,
            "YRotation": -1029,
            "ZRotation": 0
        },
        {
            "ModelId": "45085",
            "ModelIdNum": 45085,
            "ObjectType": 0,
            "XPos": 2727,
            "YPos": -226,
            "ZPos": -2267,
            "XScale": 1.0,
            "YScale": 1.0,
            "ZScale": 1.0,
            "XRotation": -1624,
            "YRotation": 0,
            "ZRotation": 0
        },
        {
            "ModelId": "45085",
            "ModelIdNum": 45085,
            "ObjectType": 0,
            "XPos": 1280,
            "YPos": -222,
            "ZPos": -2080,
            "XScale": 1.0,
            "YScale": 1.0,
            "ZScale": 1.0,
            "XRotation": -1627,
            "YRotation": -1023,
            "ZRotation": -512
        },
        {
            "ModelId": "21107",
            "ModelIdNum": 21107,
            "ObjectType": 0,
            "XPos": 1774,
            "YPos": 0,
            "ZPos": -2907,
            "XScale": 1.0,
            "YScale": 1.0,
            "ZScale": 1.0,
            "XRotation": 0,
            "YRotation": -768,
            "ZRotation": 0
        },
        {
            "ModelId": "41828",
            "ModelIdNum": 41828,
            "ObjectType": 0,
            "XPos": 1719,
            "YPos": -9,
            "ZPos": -1418,
            "XScale": 1.0,
            "YScale": 1.0,
            "ZScale": 1.0,
            "XRotation": 0,
            "YRotation": -1024,
            "ZRotation": 0
        },
        {
            "ModelId": "41828",
            "ModelIdNum": 41828,
            "ObjectType": 0,
            "XPos": 1720,
            "YPos": -9,
            "ZPos": -1440,
            "XScale": 1.0,
            "YScale": 1.0,
            "ZScale": 1.0,
            "XRotation": 0,
            "YRotation": -1024,
            "ZRotation": 0
        },
        {
            "ModelId": "41813",
            "ModelIdNum": 41813,
            "ObjectType": 0,
            "XPos": 1708,
            "YPos": -9,
            "ZPos": -1034,
            "XScale": 1.0,
            "YScale": 1.0,
            "ZScale": 1.0,
            "XRotation": 0,
            "YRotation": -1024,
            "ZRotation": 0
        },
        {
            "ModelId": "41818",
            "ModelIdNum": 41818,
            "ObjectType": 0,
            "XPos": 1867,
            "YPos": -10,
            "ZPos": -1111,
            "XScale": 1.0,
            "YScale": 1.0,
            "ZScale": 1.0,
            "XRotation": 0,
            "YRotation": -1024,
            "ZRotation": 0
        },
        {
            "ModelId": "41818",
            "ModelIdNum": 41818,
            "ObjectType": 0,
            "XPos": 1841,
            "YPos": -10,
            "ZPos": -1112,
            "XScale": 1.0,
            "YScale": 1.0,
            "ZScale": 1.0,
            "XRotation": 0,
            "YRotation": -1024,
            "ZRotation": 0
        },
        {
            "ModelId": "41818",
            "ModelIdNum": 41818,
            "ObjectType": 0,
            "XPos": 1812,
            "YPos": -10,
            "ZPos": -1112,
            "XScale": 1.0,
            "YScale": 1.0,
            "ZScale": 1.0,
            "XRotation": 0,
            "YRotation": -847,
            "ZRotation": 0
        },
        {
            "ModelId": "41828",
            "ModelIdNum": 41828,
            "ObjectType": 0,
            "XPos": 1305,
            "YPos": -9,
            "ZPos": -1359,
            "XScale": 1.0,
            "YScale": 1.0,
            "ZScale": 1.0,
            "XRotation": 0,
            "YRotation": 0,
            "ZRotation": 0
        },
        {
            "ModelId": "41828",
            "ModelIdNum": 41828,
            "ObjectType": 0,
            "XPos": 1305,
            "YPos": -9,
            "ZPos": -1378,
            "XScale": 1.0,
            "YScale": 1.0,
            "ZScale": 1.0,
            "XRotation": 0,
            "YRotation": 0,
            "ZRotation": 0
        },
        {
            "ModelId": "41828",
            "ModelIdNum": 41828,
            "ObjectType": 0,
            "XPos": 1304,
            "YPos": -29,
            "ZPos": -1370,
            "XScale": 1.0,
            "YScale": 1.0,
            "ZScale": 1.0,
            "XRotation": 0,
            "YRotation": -147,
            "ZRotation": 0
        },
        {
            "ModelId": "41828",
            "ModelIdNum": 41828,
            "ObjectType": 0,
            "XPos": 1719,
            "YPos": -29,
            "ZPos": -1433,
            "XScale": 1.0,
            "YScale": 1.0,
            "ZScale": 1.0,
            "XRotation": 0,
            "YRotation": -1024,
            "ZRotation": 0
        },
        {
            "ModelId": "41109",
            "ModelIdNum": 41109,
            "ObjectType": 0,
            "XPos": 1831,
            "YPos": -18,
            "ZPos": -1115,
            "XScale": 1.0,
            "YScale": 1.0,
            "ZScale": 1.0,
            "XRotation": 0,
            "YRotation": -2042,
            "ZRotation": 0
        },
        {
            "ModelId": "41109",
            "ModelIdNum": 41109,
            "ObjectType": 0,
            "XPos": 1746,
            "YPos": -18,
            "ZPos": -1378,
            "XScale": 1.0,
            "YScale": 1.0,
            "ZScale": 1.0,
            "XRotation": 0,
            "YRotation": -1024,
            "ZRotation": 0
        },
        {
            "ModelId": "41101",
            "ModelIdNum": 41101,
            "ObjectType": 0,
            "XPos": 1629,
            "YPos": -13,
            "ZPos": -1160,
            "XScale": 1.0,
            "YScale": 1.0,
            "ZScale": 1.0,
            "XRotation": 0,
            "YRotation": -347,
            "ZRotation": 0
        },
        {
            "ModelId": "41824",
            "ModelIdNum": 41824,
            "ObjectType": 0,
            "XPos": 1707,
            "YPos": -5,
            "ZPos": -1382,
            "XScale": 1.0,
            "YScale": 1.0,
            "ZScale": 1.0,
            "XRotation": 0,
            "YRotation": -1348,
            "ZRotation": 0
        },
        {
            "ModelId": "45085",
            "ModelIdNum": 45085,
            "ObjectType": 0,
            "XPos": 1102,
            "YPos": -220,
            "ZPos": -1670,
            "XScale": 1.0,
            "YScale": 1.0,
            "ZScale": 1.0,
            "XRotation": -1638,
            "YRotation": -1536,
            "ZRotation": -1535
        },
        {
            "ModelId": "40014",
            "ModelIdNum": 40014,
            "ObjectType": 0,
            "XPos": 3762,
            "YPos": 1,
            "ZPos": -1509,
            "XScale": 1.0,
            "YScale": 1.0,
            "ZScale": 1.0,
            "XRotation": 0,
            "YRotation": 0,
            "ZRotation": 0
        },
        {
            "ModelId": "45085",
            "ModelIdNum": 45085,
            "ObjectType": 0,
            "XPos": 3048,
            "YPos": -212,
            "ZPos": -2189,
            "XScale": 1.0,
            "YScale": 1.0,
            "ZScale": 1.0,
            "XRotation": -1536,
            "YRotation": 0,
            "ZRotation": 0
        },
        {
            "ModelId": "40013",
            "ModelIdNum": 40013,
            "ObjectType": 0,
            "XPos": -20,
            "YPos": 1,
            "ZPos": -1784,
            "XScale": 1.0,
            "YScale": 1.0,
            "ZScale": 1.0,
            "XRotation": 0,
            "YRotation": 0,
            "ZRotation": 0
        },
        {
            "ModelId": "45077",
            "ModelIdNum": 45077,
            "ObjectType": 0,
            "XPos": 63,
            "YPos": -240,
            "ZPos": -1833,
            "XScale": 1.0,
            "YScale": 1.0,
            "ZScale": 1.0,
            "XRotation": 0,
            "YRotation": 0,
            "ZRotation": 0
        },
        {
            "ModelId": "45077",
            "ModelIdNum": 45077,
            "ObjectType": 0,
            "XPos": 1069,
            "YPos": -213,
            "ZPos": -1645,
            "XScale": 1.0,
            "YScale": 1.0,
            "ZScale": 1.0,
            "XRotation": 0,
            "YRotation": 0,
            "ZRotation": 0
        },
        {
            "ModelId": "21107",
            "ModelIdNum": 21107,
            "ObjectType": 0,
            "XPos": 708,
            "YPos": 1,
            "ZPos": -2201,
            "XScale": 1.0,
            "YScale": 1.0,
            "ZScale": 1.0,
            "XRotation": 0,
            "YRotation": 0,
            "ZRotation": 0
        },
        {
            "ModelId": "45088",
            "ModelIdNum": 45088,
            "ObjectType": 0,
            "XPos": 2802,
            "YPos": 0,
            "ZPos": -2702,
            "XScale": 1.0,
            "YScale": 1.0,
            "ZScale": 1.0,
            "XRotation": 0,
            "YRotation": -540,
            "ZRotation": 0
        },
        {
            "ModelId": "40014",
            "ModelIdNum": 40014,
            "ObjectType": 0,
            "XPos": 234,
            "YPos": 1,
            "ZPos": -1784,
            "XScale": 1.0,
            "YScale": 1.0,
            "ZScale": 1.0,
            "XRotation": 0,
            "YRotation": 0,
            "ZRotation": 0
        },
        {
            "ModelId": "45074",
            "ModelIdNum": 45074,
            "ObjectType": 0,
            "XPos": 3453,
            "YPos": 1,
            "ZPos": -1572,
            "XScale": 1.0,
            "YScale": 1.0,
            "ZScale": 1.0,
            "XRotation": 0,
            "YRotation": 0,
            "ZRotation": 0
        },
        {
            "ModelId": "51109",
            "ModelIdNum": 51109,
            "ObjectType": 0,
            "XPos": 2386,
            "YPos": -12,
            "ZPos": -1917,
            "XScale": 1.0,
            "YScale": 1.0,
            "ZScale": 1.0,
            "XRotation": 0,
            "YRotation": 0,
            "ZRotation": 0
        },
        {
            "ModelId": "45076",
            "ModelIdNum": 45076,
            "ObjectType": 0,
            "XPos": 3453,
            "YPos": -116,
            "ZPos": -1572,
            "XScale": 1.0,
            "YScale": 1.0,
            "ZScale": 1.0,
            "XRotation": 0,
            "YRotation": 0,
            "ZRotation": 0
        },
        {
            "ModelId": "45077",
            "ModelIdNum": 45077,
            "ObjectType": 0,
            "XPos": 3453,
            "YPos": -228,
            "ZPos": -1572,
            "XScale": 1.0,
            "YScale": 1.0,
            "ZScale": 1.0,
            "XRotation": 0,
            "YRotation": 0,
            "ZRotation": 0
        },
        {
            "ModelId": "41830",
            "ModelIdNum": 41830,
            "ObjectType": 0,
            "XPos": 3315,
            "YPos": -5,
            "ZPos": -2934,
            "XScale": 1.0,
            "YScale": 1.0,
            "ZScale": 1.0,
            "XRotation": 0,
            "YRotation": -130,
            "ZRotation": 0
        },
        {
            "ModelId": "41050",
            "ModelIdNum": 41050,
            "ObjectType": 0,
            "XPos": 3796,
            "YPos": -11,
            "ZPos": -2995,
            "XScale": 1.0,
            "YScale": 1.0,
            "ZScale": 1.0,
            "XRotation": 0,
            "YRotation": -1735,
            "ZRotation": 0
        },
        {
            "ModelId": "41108",
            "ModelIdNum": 41108,
            "ObjectType": 0,
            "XPos": 2926,
            "YPos": -16,
            "ZPos": -2656,
            "XScale": 1.0,
            "YScale": 1.0,
            "ZScale": 1.0,
            "XRotation": 0,
            "YRotation": 0,
            "ZRotation": 0
        },
        {
            "ModelId": "41106",
            "ModelIdNum": 41106,
            "ObjectType": 0,
            "XPos": 1582,
            "YPos": -12,
            "ZPos": -2841,
            "XScale": 1.0,
            "YScale": 1.0,
            "ZScale": 1.0,
            "XRotation": 0,
            "YRotation": 0,
            "ZRotation": 0
        },
        {
            "ModelId": "41824",
            "ModelIdNum": 41824,
            "ObjectType": 0,
            "XPos": 1705,
            "YPos": -5,
            "ZPos": -1255,
            "XScale": 1.0,
            "YScale": 1.0,
            "ZScale": 1.0,
            "XRotation": 0,
            "YRotation": -1024,
            "ZRotation": 0
        },
        {
            "ModelId": "41015",
            "ModelIdNum": 41015,
            "ObjectType": 0,
            "XPos": 1315,
            "YPos": -36,
            "ZPos": -1246,
            "XScale": 1.0,
            "YScale": 1.0,
            "ZScale": 1.0,
            "XRotation": 0,
            "YRotation": -517,
            "ZRotation": 0
        },
        {
            "ModelId": "41100",
            "ModelIdNum": 41100,
            "ObjectType": 0,
            "XPos": 1130,
            "YPos": -13,
            "ZPos": -811,
            "XScale": 1.0,
            "YScale": 1.0,
            "ZScale": 1.0,
            "XRotation": 0,
            "YRotation": -420,
            "ZRotation": 0
        },
        {
            "ModelId": "41101",
            "ModelIdNum": 41101,
            "ObjectType": 0,
            "XPos": 1289,
            "YPos": -13,
            "ZPos": -1185,
            "XScale": 1.0,
            "YScale": 1.0,
            "ZScale": 1.0,
            "XRotation": 0,
            "YRotation": -1314,
            "ZRotation": 0
        },
        {
            "ModelId": "41108",
            "ModelIdNum": 41108,
            "ObjectType": 0,
            "XPos": 1599,
            "YPos": -16,
            "ZPos": -1049,
            "XScale": 1.0,
            "YScale": 1.0,
            "ZScale": 1.0,
            "XRotation": 0,
            "YRotation": -511,
            "ZRotation": 0
        },
        {
            "ModelId": "41109",
            "ModelIdNum": 41109,
            "ObjectType": 0,
            "XPos": 1744,
            "YPos": -18,
            "ZPos": -1041,
            "XScale": 1.0,
            "YScale": 1.0,
            "ZScale": 1.0,
            "XRotation": 0,
            "YRotation": -1024,
            "ZRotation": 0
        },
        {
            "ModelId": "41109",
            "ModelIdNum": 41109,
            "ObjectType": 0,
            "XPos": 1745,
            "YPos": -18,
            "ZPos": -1151,
            "XScale": 1.0,
            "YScale": 1.0,
            "ZScale": 1.0,
            "XRotation": 0,
            "YRotation": -512,
            "ZRotation": 0
        },
        {
            "ModelId": "41103",
            "ModelIdNum": 41103,
            "ObjectType": 0,
            "XPos": 1131,
            "YPos": -11,
            "ZPos": -1454,
            "XScale": 1.0,
            "YScale": 1.0,
            "ZScale": 1.0,
            "XRotation": 0,
            "YRotation": -546,
            "ZRotation": 0
        },
        {
            "ModelId": "41811",
            "ModelIdNum": 41811,
            "ObjectType": 0,
            "XPos": 1145,
            "YPos": -10,
            "ZPos": -873,
            "XScale": 1.0,
            "YScale": 1.0,
            "ZScale": 1.0,
            "XRotation": 0,
            "YRotation": 0,
            "ZRotation": 0
        },
        {
            "ModelId": "21107",
            "ModelIdNum": 21107,
            "ObjectType": 0,
            "XPos": 3138,
            "YPos": 0,
            "ZPos": -775,
            "XScale": 1.0,
            "YScale": 1.0,
            "ZScale": 1.0,
            "XRotation": 0,
            "YRotation": -301,
            "ZRotation": 0
        },
        {
            "ModelId": "41106",
            "ModelIdNum": 41106,
            "ObjectType": 0,
            "XPos": 1564,
            "YPos": -12,
            "ZPos": -2696,
            "XScale": 1.0,
            "YScale": 1.0,
            "ZScale": 1.0,
            "XRotation": 0,
            "YRotation": -1792,
            "ZRotation": 0
        },
        {
            "ModelId": "40014",
            "ModelIdNum": 40014,
            "ObjectType": 0,
            "XPos": 3269,
            "YPos": 1,
            "ZPos": -1466,
            "XScale": 1.0,
            "YScale": 1.0,
            "ZScale": 1.0,
            "XRotation": 0,
            "YRotation": 0,
            "ZRotation": 0
        },
        {
            "ModelId": "41106",
            "ModelIdNum": 41106,
            "ObjectType": 0,
            "XPos": 1643,
            "YPos": -12,
            "ZPos": -2773,
            "XScale": 1.0,
            "YScale": 1.0,
            "ZScale": 1.0,
            "XRotation": -1988,
            "YRotation": -1877,
            "ZRotation": -1987
        },
        {
            "ModelId": "41739",
            "ModelIdNum": 41739,
            "ObjectType": 0,
            "XPos": 2904,
            "YPos": -55,
            "ZPos": -175,
            "XScale": 1.0,
            "YScale": 1.0,
            "ZScale": 1.0,
            "XRotation": 0,
            "YRotation": -1840,
            "ZRotation": 0
        },
        {
            "ModelId": "21107",
            "ModelIdNum": 21107,
            "ObjectType": 0,
            "XPos": 1673,
            "YPos": 0,
            "ZPos": -2653,
            "XScale": 1.0,
            "YScale": 1.0,
            "ZScale": 1.0,
            "XRotation": 0,
            "YRotation": -256,
            "ZRotation": 0
        },
        {
            "ModelId": "40013",
            "ModelIdNum": 40013,
            "ObjectType": 0,
            "XPos": 3397,
            "YPos": 1,
            "ZPos": -1466,
            "XScale": 1.0,
            "YScale": 1.0,
            "ZScale": 1.0,
            "XRotation": 0,
            "YRotation": -1024,
            "ZRotation": 0
        },
        {
            "ModelId": "21107",
            "ModelIdNum": 21107,
            "ObjectType": 0,
            "XPos": 657,
            "YPos": 1,
            "ZPos": -745,
            "XScale": 1.0,
            "YScale": 1.0,
            "ZScale": 1.0,
            "XRotation": 0,
            "YRotation": 0,
            "ZRotation": 0
        },
        {
            "ModelId": "40013",
            "ModelIdNum": 40013,
            "ObjectType": 0,
            "XPos": 3634,
            "YPos": 1,
            "ZPos": -1509,
            "XScale": 1.0,
            "YScale": 1.0,
            "ZScale": 1.0,
            "XRotation": 0,
            "YRotation": 0,
            "ZRotation": 0
        },
        {
            "ModelId": "43727",
            "ModelIdNum": 43727,
            "ObjectType": 0,
            "XPos": 1416,
            "YPos": -63,
            "ZPos": -2525,
            "XScale": 1.0,
            "YScale": 1.0,
            "ZScale": 1.0,
            "XRotation": 0,
            "YRotation": 0,
            "ZRotation": 0
        },
        {
            "ModelId": "21107",
            "ModelIdNum": 21107,
            "ObjectType": 0,
            "XPos": 2584,
            "YPos": 1,
            "ZPos": -836,
            "XScale": 1.0,
            "YScale": 1.0,
            "ZScale": 1.0,
            "XRotation": 0,
            "YRotation": -841,
            "ZRotation": 0
        },
        {
            "ModelId": "21107",
            "ModelIdNum": 21107,
            "ObjectType": 0,
            "XPos": 1765,
            "YPos": 0,
            "ZPos": -1872,
            "XScale": 1.0,
            "YScale": 1.0,
            "ZScale": 1.0,
            "XRotation": 0,
            "YRotation": -1029,
            "ZRotation": 0
        },
        {
            "ModelId": "21107",
            "ModelIdNum": 21107,
            "ObjectType": 0,
            "XPos": 1690,
            "YPos": 0,
            "ZPos": -2993,
            "XScale": 1.0,
            "YScale": 1.0,
            "ZScale": 1.0,
            "XRotation": 0,
            "YRotation": -768,
            "ZRotation": 0
        },
        {
            "ModelId": "41108",
            "ModelIdNum": 41108,
            "ObjectType": 0,
            "XPos": 1579,
            "YPos": -16,
            "ZPos": -2892,
            "XScale": 1.0,
            "YScale": 1.0,
            "ZScale": 1.0,
            "XRotation": 0,
            "YRotation": 0,
            "ZRotation": 0
        },
        {
            "ModelId": "21106",
            "ModelIdNum": 21106,
            "ObjectType": 0,
            "XPos": 408,
            "YPos": 1,
            "ZPos": -745,
            "XScale": 1.0,
            "YScale": 1.0,
            "ZScale": 1.0,
            "XRotation": 0,
            "YRotation": 0,
            "ZRotation": 0
        },
        {
            "ModelId": "43510",
            "ModelIdNum": 43510,
            "ObjectType": 0,
            "XPos": 2757,
            "YPos": -35,
            "ZPos": -2796,
            "XScale": 1.0,
            "YScale": 1.0,
            "ZScale": 1.0,
            "XRotation": 0,
            "YRotation": -1513,
            "ZRotation": 0
        },
        {
            "ModelId": "21107",
            "ModelIdNum": 21107,
            "ObjectType": 0,
            "XPos": 2661,
            "YPos": 1,
            "ZPos": -819,
            "XScale": 1.0,
            "YScale": 1.0,
            "ZScale": 1.0,
            "XRotation": 0,
            "YRotation": -1041,
            "ZRotation": 0
        },
        {
            "ModelId": "43307",
            "ModelIdNum": 43307,
            "ObjectType": 0,
            "XPos": 3324,
            "YPos": -15,
            "ZPos": -1221,
            "XScale": 1.0,
            "YScale": 1.0,
            "ZScale": 1.0,
            "XRotation": 0,
            "YRotation": -517,
            "ZRotation": 0
        },
        {
            "ModelId": "21107",
            "ModelIdNum": 21107,
            "ObjectType": 0,
            "XPos": 280,
            "YPos": 1,
            "ZPos": -745,
            "XScale": 1.0,
            "YScale": 1.0,
            "ZScale": 1.0,
            "XRotation": 0,
            "YRotation": 0,
            "ZRotation": 0
        },
        {
            "ModelId": "43735",
            "ModelIdNum": 43735,
            "ObjectType": 0,
            "XPos": 3358,
            "YPos": -154,
            "ZPos": -901,
            "XScale": 1.0,
            "YScale": 1.0,
            "ZScale": 1.0,
            "XRotation": 0,
            "YRotation": -1541,
            "ZRotation": 0
        },
        {
            "ModelId": "40014",
            "ModelIdNum": 40014,
            "ObjectType": 0,
            "XPos": 2891,
            "YPos": 1,
            "ZPos": -1466,
            "XScale": 1.0,
            "YScale": 1.0,
            "ZScale": 1.0,
            "XRotation": 0,
            "YRotation": 0,
            "ZRotation": 0
        },
        {
            "ModelId": "21107",
            "ModelIdNum": 21107,
            "ObjectType": 0,
            "XPos": 533,
            "YPos": 1,
            "ZPos": -746,
            "XScale": 1.0,
            "YScale": 1.0,
            "ZScale": 1.0,
            "XRotation": 0,
            "YRotation": 0,
            "ZRotation": 0
        },
        {
            "ModelId": "45085",
            "ModelIdNum": 45085,
            "ObjectType": 0,
            "XPos": 3389,
            "YPos": -139,
            "ZPos": -1934,
            "XScale": 1.0,
            "YScale": 1.0,
            "ZScale": 1.0,
            "XRotation": -1536,
            "YRotation": 0,
            "ZRotation": 0
        },
        {
            "ModelId": "21106",
            "ModelIdNum": 21106,
            "ObjectType": 0,
            "XPos": 1450,
            "YPos": 0,
            "ZPos": -2514,
            "XScale": 1.0,
            "YScale": 1.0,
            "ZScale": 1.0,
            "XRotation": 0,
            "YRotation": 0,
            "ZRotation": 0
        },
        {
            "ModelId": "45085",
            "ModelIdNum": 45085,
            "ObjectType": 0,
            "XPos": 1241,
            "YPos": -219,
            "ZPos": -1371,
            "XScale": 1.0,
            "YScale": 1.0,
            "ZScale": 1.0,
            "XRotation": -1627,
            "YRotation": -1023,
            "ZRotation": -512
        },
        {
            "ModelId": "21107",
            "ModelIdNum": 21107,
            "ObjectType": 0,
            "XPos": 1600,
            "YPos": 0,
            "ZPos": -3080,
            "XScale": 1.0,
            "YScale": 1.0,
            "ZScale": 1.0,
            "XRotation": 0,
            "YRotation": -768,
            "ZRotation": 0
        },
        {
            "ModelId": "21107",
            "ModelIdNum": 21107,
            "ObjectType": 0,
            "XPos": 2497,
            "YPos": 0,
            "ZPos": -903,
            "XScale": 1.0,
            "YScale": 1.0,
            "ZScale": 1.0,
            "XRotation": 0,
            "YRotation": -790,
            "ZRotation": 0
        },
        {
            "ModelId": "41815",
            "ModelIdNum": 41815,
            "ObjectType": 0,
            "XPos": 2926,
            "YPos": -5,
            "ZPos": -2877,
            "XScale": 1.0,
            "YScale": 1.0,
            "ZScale": 1.0,
            "XRotation": 0,
            "YRotation": 0,
            "ZRotation": 0
        },
        {
            "ModelId": "41815",
            "ModelIdNum": 41815,
            "ObjectType": 0,
            "XPos": 2961,
            "YPos": -5,
            "ZPos": -2871,
            "XScale": 1.0,
            "YScale": 1.0,
            "ZScale": 1.0,
            "XRotation": 0,
            "YRotation": -79,
            "ZRotation": 0
        },
        {
            "ModelId": "41815",
            "ModelIdNum": 41815,
            "ObjectType": 0,
            "XPos": 2956,
            "YPos": -17,
            "ZPos": -2872,
            "XScale": 1.0,
            "YScale": 1.0,
            "ZScale": 1.0,
            "XRotation": 0,
            "YRotation": -79,
            "ZRotation": 0
        },
        {
            "ModelId": "43307",
            "ModelIdNum": 43307,
            "ObjectType": 0,
            "XPos": 683,
            "YPos": -15,
            "ZPos": -1372,
            "XScale": 1.0,
            "YScale": 1.0,
            "ZScale": 1.0,
            "XRotation": 0,
            "YRotation": -483,
            "ZRotation": 0
        },
        {
            "ModelId": "43307",
            "ModelIdNum": 43307,
            "ObjectType": 0,
            "XPos": 684,
            "YPos": -15,
            "ZPos": -977,
            "XScale": 1.0,
            "YScale": 1.0,
            "ZScale": 1.0,
            "XRotation": 0,
            "YRotation": -483,
            "ZRotation": 0
        },
        {
            "ModelId": "51109",
            "ModelIdNum": 51109,
            "ObjectType": 0,
            "XPos": 1726,
            "YPos": -12,
            "ZPos": -1655,
            "XScale": 1.0,
            "YScale": 1.0,
            "ZScale": 1.0,
            "XRotation": 0,
            "YRotation": -1553,
            "ZRotation": 0
        },
        {
            "ModelId": "51109",
            "ModelIdNum": 51109,
            "ObjectType": 0,
            "XPos": 913,
            "YPos": -12,
            "ZPos": -2210,
            "XScale": 1.0,
            "YScale": 1.0,
            "ZScale": 1.0,
            "XRotation": 0,
            "YRotation": 0,
            "ZRotation": 0
        },
        {
            "ModelId": "41739",
            "ModelIdNum": 41739,
            "ObjectType": 0,
            "XPos": 1433,
            "YPos": -55,
            "ZPos": -175,
            "XScale": 1.0,
            "YScale": 1.0,
            "ZScale": 1.0,
            "XRotation": 0,
            "YRotation": -232,
            "ZRotation": 0
        },
        {
            "ModelId": "45085",
            "ModelIdNum": 45085,
            "ObjectType": 0,
            "XPos": 3048,
            "YPos": -253,
            "ZPos": -1929,
            "XScale": 1.0,
            "YScale": 1.0,
            "ZScale": 1.0,
            "XRotation": -1638,
            "YRotation": -1024,
            "ZRotation": -1024
        },
        {
            "ModelId": "41822",
            "ModelIdNum": 41822,
            "ObjectType": 0,
            "XPos": 1752,
            "YPos": -14,
            "ZPos": -1186,
            "XScale": 1.0,
            "YScale": 1.0,
            "ZScale": 1.0,
            "XRotation": 0,
            "YRotation": -1024,
            "ZRotation": 0
        },
        {
            "ModelId": "41818",
            "ModelIdNum": 41818,
            "ObjectType": 0,
            "XPos": 1785,
            "YPos": -10,
            "ZPos": -1049,
            "XScale": 1.0,
            "YScale": 1.0,
            "ZScale": 1.0,
            "XRotation": 0,
            "YRotation": -1052,
            "ZRotation": 0
        },
        {
            "ModelId": "41818",
            "ModelIdNum": 41818,
            "ObjectType": 0,
            "XPos": 1787,
            "YPos": -10,
            "ZPos": -1371,
            "XScale": 1.0,
            "YScale": 1.0,
            "ZScale": 1.0,
            "XRotation": 0,
            "YRotation": -1024,
            "ZRotation": 0
        },
        {
            "ModelId": "41818",
            "ModelIdNum": 41818,
            "ObjectType": 0,
            "XPos": 1757,
            "YPos": -10,
            "ZPos": -1373,
            "XScale": 1.0,
            "YScale": 1.0,
            "ZScale": 1.0,
            "XRotation": 0,
            "YRotation": -847,
            "ZRotation": 0
        },
        {
            "ModelId": "41821",
            "ModelIdNum": 41821,
            "ObjectType": 0,
            "XPos": 1786,
            "YPos": -3,
            "ZPos": -1107,
            "XScale": 1.0,
            "YScale": 1.0,
            "ZScale": 1.0,
            "XRotation": 0,
            "YRotation": -1024,
            "ZRotation": 0
        },
        {
            "ModelId": "41821",
            "ModelIdNum": 41821,
            "ObjectType": 0,
            "XPos": 1782,
            "YPos": -3,
            "ZPos": -1025,
            "XScale": 1.0,
            "YScale": 1.0,
            "ZScale": 1.0,
            "XRotation": 0,
            "YRotation": -938,
            "ZRotation": 0
        },
        {
            "ModelId": "41824",
            "ModelIdNum": 41824,
            "ObjectType": 0,
            "XPos": 1749,
            "YPos": -5,
            "ZPos": -1028,
            "XScale": 1.0,
            "YScale": 1.0,
            "ZScale": 1.0,
            "XRotation": 0,
            "YRotation": -1024,
            "ZRotation": 0
        },
        {
            "ModelId": "41824",
            "ModelIdNum": 41824,
            "ObjectType": 0,
            "XPos": 1743,
            "YPos": -5,
            "ZPos": -1100,
            "XScale": 1.0,
            "YScale": 1.0,
            "ZScale": 1.0,
            "XRotation": 0,
            "YRotation": -1024,
            "ZRotation": 0
        },
        {
            "ModelId": "45085",
            "ModelIdNum": 45085,
            "ObjectType": 0,
            "XPos": 2727,
            "YPos": -212,
            "ZPos": -2004,
            "XScale": 1.0,
            "YScale": 1.0,
            "ZScale": 1.0,
            "XRotation": -1590,
            "YRotation": -1024,
            "ZRotation": -1024
        },
        {
            "ModelId": "41825",
            "ModelIdNum": 41825,
            "ObjectType": 0,
            "XPos": 2952,
            "YPos": -5,
            "ZPos": -2844,
            "XScale": 1.0,
            "YScale": 1.0,
            "ZScale": 1.0,
            "XRotation": 0,
            "YRotation": -1826,
            "ZRotation": 0
        },
        {
            "ModelId": "41828",
            "ModelIdNum": 41828,
            "ObjectType": 0,
            "XPos": 2945,
            "YPos": -9,
            "ZPos": -2816,
            "XScale": 1.0,
            "YScale": 1.0,
            "ZScale": 1.0,
            "XRotation": 0,
            "YRotation": -1928,
            "ZRotation": 0
        },
        {
            "ModelId": "41828",
            "ModelIdNum": 41828,
            "ObjectType": 0,
            "XPos": 2858,
            "YPos": -9,
            "ZPos": -2666,
            "XScale": 1.0,
            "YScale": 1.0,
            "ZScale": 1.0,
            "XRotation": 0,
            "YRotation": -2036,
            "ZRotation": 0
        },
        {
            "ModelId": "53104",
            "ModelIdNum": 53104,
            "ObjectType": 0,
            "XPos": 1233,
            "YPos": -2,
            "ZPos": -1267,
            "XScale": 1.0,
            "YScale": 1.0,
            "ZScale": 1.0,
            "XRotation": 0,
            "YRotation": -1018,
            "ZRotation": 0
        },
        {
            "ModelId": "41108",
            "ModelIdNum": 41108,
            "ObjectType": 0,
            "XPos": 1610,
            "YPos": -16,
            "ZPos": -2736,
            "XScale": 1.0,
            "YScale": 1.0,
            "ZScale": 1.0,
            "XRotation": 0,
            "YRotation": -1792,
            "ZRotation": 0
        },
        {
            "ModelId": "45077",
            "ModelIdNum": 45077,
            "ObjectType": 0,
            "XPos": 3568,
            "YPos": -109,
            "ZPos": -2593,
            "XScale": 1.0,
            "YScale": 1.0,
            "ZScale": 1.0,
            "XRotation": 0,
            "YRotation": 0,
            "ZRotation": 0
        },
        {
            "ModelId": "45077",
            "ModelIdNum": 45077,
            "ObjectType": 0,
            "XPos": 1350,
            "YPos": -240,
            "ZPos": -1844,
            "XScale": 1.0,
            "YScale": 1.0,
            "ZScale": 1.0,
            "XRotation": 0,
            "YRotation": 0,
            "ZRotation": 0
        },
        {
            "ModelId": "41220",
            "ModelIdNum": 41220,
            "ObjectType": 0,
            "XPos": 2959,
            "YPos": -22,
            "ZPos": -1275,
            "XScale": 1.0,
            "YScale": 1.0,
            "ZScale": 1.0,
            "XRotation": 0,
            "YRotation": -2030,
            "ZRotation": 0
        },
        {
            "ModelId": "21107",
            "ModelIdNum": 21107,
            "ObjectType": 0,
            "XPos": 2785,
            "YPos": 1,
            "ZPos": -823,
            "XScale": 1.0,
            "YScale": 1.0,
            "ZScale": 1.0,
            "XRotation": 0,
            "YRotation": -1024,
            "ZRotation": 0
        },
        {
            "ModelId": "45077",
            "ModelIdNum": 45077,
            "ObjectType": 0,
            "XPos": 1350,
            "YPos": -380,
            "ZPos": -1742,
            "XScale": 1.0,
            "YScale": 1.0,
            "ZScale": 1.0,
            "XRotation": 0,
            "YRotation": 0,
            "ZRotation": 0
        },
        {
            "ModelId": "45077",
            "ModelIdNum": 45077,
            "ObjectType": 0,
            "XPos": 1350,
            "YPos": -380,
            "ZPos": -1350,
            "XScale": 1.0,
            "YScale": 1.0,
            "ZScale": 1.0,
            "XRotation": 0,
            "YRotation": 0,
            "ZRotation": 0
        },
        {
            "ModelId": "21107",
            "ModelIdNum": 21107,
            "ObjectType": 0,
            "XPos": 2459,
            "YPos": 1,
            "ZPos": -967,
            "XScale": 1.0,
            "YScale": 1.0,
            "ZScale": 1.0,
            "XRotation": 0,
            "YRotation": -597,
            "ZRotation": 0
        },
        {
            "ModelId": "45077",
            "ModelIdNum": 45077,
            "ObjectType": 0,
            "XPos": 427,
            "YPos": -354,
            "ZPos": -2910,
            "XScale": 1.0,
            "YScale": 1.0,
            "ZScale": 1.0,
            "XRotation": 0,
            "YRotation": 0,
            "ZRotation": 0
        },
        {
            "ModelId": "45077",
            "ModelIdNum": 45077,
            "ObjectType": 0,
            "XPos": 2624,
            "YPos": -380,
            "ZPos": -1825,
            "XScale": 1.0,
            "YScale": 1.0,
            "ZScale": 1.0,
            "XRotation": 0,
            "YRotation": 0,
            "ZRotation": 0
        },
        {
            "ModelId": "45077",
            "ModelIdNum": 45077,
            "ObjectType": 0,
            "XPos": 3038,
            "YPos": -380,
            "ZPos": -1584,
            "XScale": 1.0,
            "YScale": 1.0,
            "ZScale": 1.0,
            "XRotation": 0,
            "YRotation": 0,
            "ZRotation": 0
        },
        {
            "ModelId": "45077",
            "ModelIdNum": 45077,
            "ObjectType": 0,
            "XPos": 1069,
            "YPos": -240,
            "ZPos": -1128,
            "XScale": 1.0,
            "YScale": 1.0,
            "ZScale": 1.0,
            "XRotation": 0,
            "YRotation": 0,
            "ZRotation": 0
        },
        {
            "ModelId": "45077",
            "ModelIdNum": 45077,
            "ObjectType": 0,
            "XPos": 2690,
            "YPos": -380,
            "ZPos": -1325,
            "XScale": 1.0,
            "YScale": 1.0,
            "ZScale": 1.0,
            "XRotation": 0,
            "YRotation": 0,
            "ZRotation": 0
        },
        {
            "ModelId": "53100",
            "ModelIdNum": 53100,
            "ObjectType": 0,
            "XPos": 1198,
            "YPos": -2,
            "ZPos": -1554,
            "XScale": 1.0,
            "YScale": 1.0,
            "ZScale": 1.0,
            "XRotation": 0,
            "YRotation": 0,
            "ZRotation": 0
        },
        {
            "ModelId": "41125",
            "ModelIdNum": 41125,
            "ObjectType": 0,
            "XPos": 1143,
            "YPos": -11,
            "ZPos": -1649,
            "XScale": 1.0,
            "YScale": 1.0,
            "ZScale": 1.0,
            "XRotation": 0,
            "YRotation": -381,
            "ZRotation": 0
        },
        {
            "ModelId": "53108",
            "ModelIdNum": 53108,
            "ObjectType": 0,
            "XPos": 1194,
            "YPos": -2,
            "ZPos": -934,
            "XScale": 1.0,
            "YScale": 1.0,
            "ZScale": 1.0,
            "XRotation": 0,
            "YRotation": 0,
            "ZRotation": 0
        },
        {
            "ModelId": "41009",
            "ModelIdNum": 41009,
            "ObjectType": 0,
            "XPos": 1138,
            "YPos": -20,
            "ZPos": -1612,
            "XScale": 1.0,
            "YScale": 1.0,
            "ZScale": 1.0,
            "XRotation": 0,
            "YRotation": -1928,
            "ZRotation": 0
        },
        {
            "ModelId": "41013",
            "ModelIdNum": 41013,
            "ObjectType": 0,
            "XPos": 1122,
            "YPos": -32,
            "ZPos": -1539,
            "XScale": 1.0,
            "YScale": 1.0,
            "ZScale": 1.0,
            "XRotation": 0,
            "YRotation": -1530,
            "ZRotation": 0
        },
        {
            "ModelId": "51109",
            "ModelIdNum": 51109,
            "ObjectType": 0,
            "XPos": 3212,
            "YPos": -12,
            "ZPos": -2689,
            "XScale": 1.0,
            "YScale": 1.0,
            "ZScale": 1.0,
            "XRotation": 0,
            "YRotation": -1649,
            "ZRotation": 0
        },
        {
            "ModelId": "40014",
            "ModelIdNum": 40014,
            "ObjectType": 0,
            "XPos": 360,
            "YPos": 1,
            "ZPos": -1784,
            "XScale": 1.0,
            "YScale": 1.0,
            "ZScale": 1.0,
            "XRotation": 0,
            "YRotation": 0,
            "ZRotation": 0
        },
        {
            "ModelId": "40014",
            "ModelIdNum": 40014,
            "ObjectType": 0,
            "XPos": 486,
            "YPos": 1,
            "ZPos": -1784,
            "XScale": 1.0,
            "YScale": 1.0,
            "ZScale": 1.0,
            "XRotation": 0,
            "YRotation": 0,
            "ZRotation": 0
        },
        {
            "ModelId": "40013",
            "ModelIdNum": 40013,
            "ObjectType": 0,
            "XPos": 614,
            "YPos": 1,
            "ZPos": -1784,
            "XScale": 1.0,
            "YScale": 1.0,
            "ZScale": 1.0,
            "XRotation": 0,
            "YRotation": -1024,
            "ZRotation": 0
        },
        {
            "ModelId": "45074",
            "ModelIdNum": 45074,
            "ObjectType": 0,
            "XPos": 3573,
            "YPos": 19,
            "ZPos": -2593,
            "XScale": 1.0,
            "YScale": 1.0,
            "ZScale": 1.0,
            "XRotation": 0,
            "YRotation": 0,
            "ZRotation": 0
        },
        {
            "ModelId": "45077",
            "ModelIdNum": 45077,
            "ObjectType": 0,
            "XPos": 3044,
            "YPos": -72,
            "ZPos": -2924,
            "XScale": 1.0,
            "YScale": 1.0,
            "ZScale": 1.0,
            "XRotation": 0,
            "YRotation": 0,
            "ZRotation": 0
        },
        {
            "ModelId": "41013",
            "ModelIdNum": 41013,
            "ObjectType": 0,
            "XPos": 1631,
            "YPos": -32,
            "ZPos": -1399,
            "XScale": 1.0,
            "YScale": 1.0,
            "ZScale": 1.0,
            "XRotation": 0,
            "YRotation": -1024,
            "ZRotation": 0
        },
        {
            "ModelId": "41011",
            "ModelIdNum": 41011,
            "ObjectType": 0,
            "XPos": 1623,
            "YPos": -32,
            "ZPos": -1197,
            "XScale": 1.0,
            "YScale": 1.0,
            "ZScale": 1.0,
            "XRotation": 0,
            "YRotation": -1024,
            "ZRotation": 0
        },
        {
            "ModelId": "41108",
            "ModelIdNum": 41108,
            "ObjectType": 0,
            "XPos": 1709,
            "YPos": -16,
            "ZPos": -1291,
            "XScale": 1.0,
            "YScale": 1.0,
            "ZScale": 1.0,
            "XRotation": 0,
            "YRotation": -511,
            "ZRotation": 0
        },
        {
            "ModelId": "21107",
            "ModelIdNum": 21107,
            "ObjectType": 0,
            "XPos": 1759,
            "YPos": 0,
            "ZPos": -2738,
            "XScale": 1.0,
            "YScale": 1.0,
            "ZScale": 1.0,
            "XRotation": 0,
            "YRotation": -256,
            "ZRotation": 0
        },
        {
            "ModelId": "21107",
            "ModelIdNum": 21107,
            "ObjectType": 0,
            "XPos": 1864,
            "YPos": 1,
            "ZPos": -2096,
            "XScale": 1.0,
            "YScale": 1.0,
            "ZScale": 1.0,
            "XRotation": 0,
            "YRotation": -512,
            "ZRotation": 0
        },
        {
            "ModelId": "45077",
            "ModelIdNum": 45077,
            "ObjectType": 0,
            "XPos": 2645,
            "YPos": -380,
            "ZPos": -2552,
            "XScale": 1.0,
            "YScale": 1.0,
            "ZScale": 1.0,
            "XRotation": 0,
            "YRotation": 0,
            "ZRotation": 0
        },
        {
            "ModelId": "45085",
            "ModelIdNum": 45085,
            "ObjectType": 0,
            "XPos": 3389,
            "YPos": -220,
            "ZPos": -2184,
            "XScale": 1.0,
            "YScale": 1.0,
            "ZScale": 1.0,
            "XRotation": -1737,
            "YRotation": 0,
            "ZRotation": 0
        },
        {
            "ModelId": "40014",
            "ModelIdNum": 40014,
            "ObjectType": 0,
            "XPos": 3143,
            "YPos": 1,
            "ZPos": -1466,
            "XScale": 1.0,
            "YScale": 1.0,
            "ZScale": 1.0,
            "XRotation": 0,
            "YRotation": 0,
            "ZRotation": 0
        },
        {
            "ModelId": "40014",
            "ModelIdNum": 40014,
            "ObjectType": 0,
            "XPos": 4014,
            "YPos": 1,
            "ZPos": -1509,
            "XScale": 1.0,
            "YScale": 1.0,
            "ZScale": 1.0,
            "XRotation": 0,
            "YRotation": 0,
            "ZRotation": 0
        },
        {
            "ModelId": "45077",
            "ModelIdNum": 45077,
            "ObjectType": 0,
            "XPos": 3030,
            "YPos": -380,
            "ZPos": -2560,
            "XScale": 1.0,
            "YScale": 1.0,
            "ZScale": 1.0,
            "XRotation": 0,
            "YRotation": 0,
            "ZRotation": 0
        },
        {
            "ModelId": "21107",
            "ModelIdNum": 21107,
            "ObjectType": 0,
            "XPos": 3168,
            "YPos": 1,
            "ZPos": -934,
            "XScale": 1.0,
            "YScale": 1.0,
            "ZScale": 1.0,
            "XRotation": 0,
            "YRotation": -1132,
            "ZRotation": 0
        },
        {
            "ModelId": "45077",
            "ModelIdNum": 45077,
            "ObjectType": 0,
            "XPos": 808,
            "YPos": -82,
            "ZPos": -3290,
            "XScale": 1.0,
            "YScale": 1.0,
            "ZScale": 1.0,
            "XRotation": 0,
            "YRotation": 0,
            "ZRotation": 0
        },
        {
            "ModelId": "41821",
            "ModelIdNum": 41821,
            "ObjectType": 0,
            "XPos": 1733,
            "YPos": -3,
            "ZPos": -1370,
            "XScale": 1.0,
            "YScale": 1.0,
            "ZScale": 1.0,
            "XRotation": 0,
            "YRotation": -1024,
            "ZRotation": 0
        },
        {
            "ModelId": "41821",
            "ModelIdNum": 41821,
            "ObjectType": 0,
            "XPos": 1714,
            "YPos": -3,
            "ZPos": -1303,
            "XScale": 1.0,
            "YScale": 1.0,
            "ZScale": 1.0,
            "XRotation": 0,
            "YRotation": -1024,
            "ZRotation": 0
        },
        {
            "ModelId": "45085",
            "ModelIdNum": 45085,
            "ObjectType": 0,
            "XPos": 761,
            "YPos": -215,
            "ZPos": -1736,
            "XScale": 1.0,
            "YScale": 1.0,
            "ZScale": 1.0,
            "XRotation": -1581,
            "YRotation": -1536,
            "ZRotation": -1535
        },
        {
            "ModelId": "45085",
            "ModelIdNum": 45085,
            "ObjectType": 0,
            "XPos": 1241,
            "YPos": -214,
            "ZPos": -1029,
            "XScale": 1.0,
            "YScale": 1.0,
            "ZScale": 1.0,
            "XRotation": -1627,
            "YRotation": -1024,
            "ZRotation": -512
        },
        {
            "ModelId": "45077",
            "ModelIdNum": 45077,
            "ObjectType": 0,
            "XPos": 3412,
            "YPos": -240,
            "ZPos": -2585,
            "XScale": 1.0,
            "YScale": 1.0,
            "ZScale": 1.0,
            "XRotation": 0,
            "YRotation": 0,
            "ZRotation": 0
        },
        {
            "ModelId": "21107",
            "ModelIdNum": 21107,
            "ObjectType": 0,
            "XPos": 1586,
            "YPos": 0,
            "ZPos": -2566,
            "XScale": 1.0,
            "YScale": 1.0,
            "ZScale": 1.0,
            "XRotation": 0,
            "YRotation": -256,
            "ZRotation": 0
        },
        {
            "ModelId": "41103",
            "ModelIdNum": 41103,
            "ObjectType": 0,
            "XPos": 1631,
            "YPos": -11,
            "ZPos": -1238,
            "XScale": 1.0,
            "YScale": 1.0,
            "ZScale": 1.0,
            "XRotation": 0,
            "YRotation": -676,
            "ZRotation": 0
        },
        {
            "ModelId": "41812",
            "ModelIdNum": 41812,
            "ObjectType": 0,
            "XPos": 1708,
            "YPos": -11,
            "ZPos": -1280,
            "XScale": 1.0,
            "YScale": 1.0,
            "ZScale": 1.0,
            "XRotation": 0,
            "YRotation": -1024,
            "ZRotation": 0
        },
        {
            "ModelId": "41826",
            "ModelIdNum": 41826,
            "ObjectType": 0,
            "XPos": 1752,
            "YPos": -7,
            "ZPos": -1153,
            "XScale": 1.0,
            "YScale": 1.0,
            "ZScale": 1.0,
            "XRotation": 0,
            "YRotation": -1024,
            "ZRotation": 0
        },
        {
            "ModelId": "40014",
            "ModelIdNum": 40014,
            "ObjectType": 0,
            "XPos": 108,
            "YPos": 1,
            "ZPos": -1784,
            "XScale": 1.0,
            "YScale": 1.0,
            "ZScale": 1.0,
            "XRotation": 0,
            "YRotation": 0,
            "ZRotation": 0
        },
        {
            "ModelId": "21107",
            "ModelIdNum": 21107,
            "ObjectType": 0,
            "XPos": 589,
            "YPos": 1,
            "ZPos": -2204,
            "XScale": 1.0,
            "YScale": 1.0,
            "ZScale": 1.0,
            "XRotation": 0,
            "YRotation": -2030,
            "ZRotation": 0
        },
        {
            "ModelId": "753",
            "ModelIdNum": 753,
            "ObjectType": 0,
            "XPos": 3928,
            "YPos": 1,
            "ZPos": -914,
            "XScale": 1.0,
            "YScale": 1.0,
            "ZScale": 1.0,
            "XRotation": 0,
            "YRotation": -1541,
            "ZRotation": 0
        },
        {
            "ModelId": "41106",
            "ModelIdNum": 41106,
            "ObjectType": 0,
            "XPos": 1582,
            "YPos": -12,
            "ZPos": -2949,
            "XScale": 1.0,
            "YScale": 1.0,
            "ZScale": 1.0,
            "XRotation": 0,
            "YRotation": 0,
            "ZRotation": 0
        },
        {
            "ModelId": "40013",
            "ModelIdNum": 40013,
            "ObjectType": 0,
            "XPos": 2763,
            "YPos": 1,
            "ZPos": -1466,
            "XScale": 1.0,
            "YScale": 1.0,
            "ZScale": 1.0,
            "XRotation": 0,
            "YRotation": 0,
            "ZRotation": 0
        },
        {
            "ModelId": "40013",
            "ModelIdNum": 40013,
            "ObjectType": 0,
            "XPos": 4142,
            "YPos": 1,
            "ZPos": -1509,
            "XScale": 1.0,
            "YScale": 1.0,
            "ZScale": 1.0,
            "XRotation": 0,
            "YRotation": -1024,
            "ZRotation": 0
        },
        {
            "ModelId": "21107",
            "ModelIdNum": 21107,
            "ObjectType": 0,
            "XPos": 163,
            "YPos": 1,
            "ZPos": -746,
            "XScale": 1.0,
            "YScale": 1.0,
            "ZScale": 1.0,
            "XRotation": 0,
            "YRotation": 0,
            "ZRotation": 0
        },
        {
            "ModelId": "21107",
            "ModelIdNum": 21107,
            "ObjectType": 0,
            "XPos": 344,
            "YPos": 1,
            "ZPos": -2230,
            "XScale": 1.0,
            "YScale": 1.0,
            "ZScale": 1.0,
            "XRotation": 0,
            "YRotation": -1507,
            "ZRotation": 0
        },
        {
            "ModelId": "40014",
            "ModelIdNum": 40014,
            "ObjectType": 0,
            "XPos": 3017,
            "YPos": 1,
            "ZPos": -1466,
            "XScale": 1.0,
            "YScale": 1.0,
            "ZScale": 1.0,
            "XRotation": 0,
            "YRotation": 0,
            "ZRotation": 0
        }
    ],
    "MiscFlatObjectRecords": [
        {
            "Position": 0,
            "XPos": 1286,
            "YPos": -2,
            "ZPos": -1280,
            "TextureArchive": 184,
            "TextureRecord": 21,
            "FactionID": 0,
            "Flags": 0
        },
        {
            "Position": 0,
            "XPos": 1351,
            "YPos": -2,
            "ZPos": -2520,
            "TextureArchive": 1025,
            "TextureRecord": 1,
            "FactionID": 0,
            "Flags": 0
        },
        {
            "Position": 0,
            "XPos": 1518,
            "YPos": -2,
            "ZPos": -2611,
            "TextureArchive": 1025,
            "TextureRecord": 2,
            "FactionID": 0,
            "Flags": 0
        },
        {
            "Position": 0,
            "XPos": 3307,
            "YPos": -2,
            "ZPos": -986,
            "TextureArchive": 1025,
            "TextureRecord": 4,
            "FactionID": 0,
            "Flags": 0
        },
        {
            "Position": 0,
            "XPos": 3310,
            "YPos": -2,
            "ZPos": -798,
            "TextureArchive": 1025,
            "TextureRecord": 1,
            "FactionID": 0,
            "Flags": 0
        },
        {
            "Position": 0,
            "XPos": 1705,
            "YPos": -36,
            "ZPos": -1032,
            "TextureArchive": 1021,
            "TextureRecord": 1,
            "FactionID": 0,
            "Flags": 0
        },
        {
            "Position": 0,
            "XPos": 1854,
            "YPos": -2,
            "ZPos": -1372,
            "TextureArchive": 1025,
            "TextureRecord": 1,
            "FactionID": 0,
            "Flags": 0
        },
        {
            "Position": 0,
            "XPos": 1746,
            "YPos": -37,
            "ZPos": -1178,
            "TextureArchive": 1021,
            "TextureRecord": 5,
            "FactionID": 0,
            "Flags": 0
        },
        {
            "Position": 0,
            "XPos": 1681,
            "YPos": -4,
            "ZPos": -954,
            "TextureArchive": 205,
            "TextureRecord": 0,
            "FactionID": 0,
            "Flags": 0
        },
        {
            "Position": 0,
            "XPos": 1771,
            "YPos": -37,
            "ZPos": -1053,
            "TextureArchive": 1021,
            "TextureRecord": 0,
            "FactionID": 0,
            "Flags": 0
        },
        {
            "Position": 0,
            "XPos": 1792,
            "YPos": -37,
            "ZPos": -1052,
            "TextureArchive": 1021,
            "TextureRecord": 0,
            "FactionID": 0,
            "Flags": 0
        },
        {
            "Position": 0,
            "XPos": 1748,
            "YPos": -36,
            "ZPos": -1050,
            "TextureArchive": 1021,
            "TextureRecord": 1,
            "FactionID": 0,
            "Flags": 0
        },
        {
            "Position": 0,
            "XPos": 1730,
            "YPos": -36,
            "ZPos": -1052,
            "TextureArchive": 1021,
            "TextureRecord": 1,
            "FactionID": 0,
            "Flags": 0
        },
        {
            "Position": 0,
            "XPos": 1729,
            "YPos": -6,
            "ZPos": -991,
            "TextureArchive": 205,
            "TextureRecord": 0,
            "FactionID": 0,
            "Flags": 0
        },
        {
            "Position": 0,
            "XPos": 1801,
            "YPos": -36,
            "ZPos": -1107,
            "TextureArchive": 1021,
            "TextureRecord": 14,
            "FactionID": 0,
            "Flags": 0
        },
        {
            "Position": 0,
            "XPos": 1872,
            "YPos": -36,
            "ZPos": -1113,
            "TextureArchive": 1021,
            "TextureRecord": 14,
            "FactionID": 0,
            "Flags": 0
        },
        {
            "Position": 7658,
            "XPos": 1653,
            "YPos": -4,
            "ZPos": -1190,
            "TextureArchive": 199,
            "TextureRecord": 10,
            "FactionID": 0,
            "Flags": 0
        },
        {
            "Position": 0,
            "XPos": 1728,
            "YPos": -36,
            "ZPos": -1029,
            "TextureArchive": 1021,
            "TextureRecord": 1,
            "FactionID": 0,
            "Flags": 0
        },
        {
            "Position": 0,
            "XPos": 1708,
            "YPos": -36,
            "ZPos": -1052,
            "TextureArchive": 1021,
            "TextureRecord": 1,
            "FactionID": 0,
            "Flags": 0
        },
        {
            "Position": 0,
            "XPos": 3006,
            "YPos": -1,
            "ZPos": -2859,
            "TextureArchive": 204,
            "TextureRecord": 0,
            "FactionID": 0,
            "Flags": 0
        },
        {
            "Position": 0,
            "XPos": 3399,
            "YPos": -1,
            "ZPos": -2768,
            "TextureArchive": 204,
            "TextureRecord": 0,
            "FactionID": 0,
            "Flags": 0
        },
        {
            "Position": 0,
            "XPos": 3384,
            "YPos": -1,
            "ZPos": -2727,
            "TextureArchive": 204,
            "TextureRecord": 0,
            "FactionID": 0,
            "Flags": 0
        },
        {
            "Position": 0,
            "XPos": 3326,
            "YPos": -25,
            "ZPos": -2746,
            "TextureArchive": 218,
            "TextureRecord": 6,
            "FactionID": 0,
            "Flags": 0
        },
        {
            "Position": 0,
            "XPos": 2710,
            "YPos": -1,
            "ZPos": -2998,
            "TextureArchive": 1025,
            "TextureRecord": 0,
            "FactionID": 0,
            "Flags": 0
        },
        {
            "Position": 0,
            "XPos": 1147,
            "YPos": -2,
            "ZPos": -1566,
            "TextureArchive": 184,
            "TextureRecord": 22,
            "FactionID": 0,
            "Flags": 35
        },
        {
            "Position": 0,
            "XPos": 1139,
            "YPos": -2,
            "ZPos": -942,
            "TextureArchive": 183,
            "TextureRecord": 12,
            "FactionID": 0,
            "Flags": 0
        },
        {
            "Position": 0,
            "XPos": 3171,
            "YPos": -2,
            "ZPos": -3174,
            "TextureArchive": 184,
            "TextureRecord": 9,
            "FactionID": 0,
            "Flags": 0
        },
        {
            "Position": 0,
            "XPos": 3798,
            "YPos": -1,
            "ZPos": -3289,
            "TextureArchive": 1025,
            "TextureRecord": 0,
            "FactionID": 0,
            "Flags": 0
        },
        {
            "Position": 0,
            "XPos": 3923,
            "YPos": -1,
            "ZPos": -2991,
            "TextureArchive": 1025,
            "TextureRecord": 3,
            "FactionID": 0,
            "Flags": 0
        },
        {
            "Position": 0,
            "XPos": 4014,
            "YPos": -1,
            "ZPos": -2834,
            "TextureArchive": 1025,
            "TextureRecord": 3,
            "FactionID": 0,
            "Flags": 0
        },
        {
            "Position": 0,
            "XPos": 1185,
            "YPos": -47,
            "ZPos": -1531,
            "TextureArchive": 204,
            "TextureRecord": 0,
            "FactionID": 0,
            "Flags": 0
        },
        {
            "Position": 0,
            "XPos": 1181,
            "YPos": -48,
            "ZPos": -1589,
            "TextureArchive": 205,
            "TextureRecord": 8,
            "FactionID": 0,
            "Flags": 0
        },
        {
            "Position": 0,
            "XPos": 1245,
            "YPos": -48,
            "ZPos": -1298,
            "TextureArchive": 208,
            "TextureRecord": 6,
            "FactionID": 0,
            "Flags": 0
        },
        {
            "Position": 0,
            "XPos": 1239,
            "YPos": -48,
            "ZPos": -1229,
            "TextureArchive": 208,
            "TextureRecord": 3,
            "FactionID": 0,
            "Flags": 0
        },
        {
            "Position": 0,
            "XPos": 1192,
            "YPos": -47,
            "ZPos": -963,
            "TextureArchive": 211,
            "TextureRecord": 49,
            "FactionID": 0,
            "Flags": 0
        },
        {
            "Position": 0,
            "XPos": 1595,
            "YPos": -4,
            "ZPos": -1160,
            "TextureArchive": 205,
            "TextureRecord": 0,
            "FactionID": 0,
            "Flags": 0
        },
        {
            "Position": 0,
            "XPos": 1853,
            "YPos": -2,
            "ZPos": -1021,
            "TextureArchive": 1025,
            "TextureRecord": 1,
            "FactionID": 0,
            "Flags": 0
        },
        {
            "Position": 0,
            "XPos": 1752,
            "YPos": -36,
            "ZPos": -1372,
            "TextureArchive": 204,
            "TextureRecord": 4,
            "FactionID": 0,
            "Flags": 0
        },
        {
            "Position": 0,
            "XPos": 1838,
            "YPos": -36,
            "ZPos": -1111,
            "TextureArchive": 1021,
            "TextureRecord": 15,
            "FactionID": 0,
            "Flags": 0
        },
        {
            "Position": 0,
            "XPos": 1746,
            "YPos": -37,
            "ZPos": -1139,
            "TextureArchive": 1021,
            "TextureRecord": 5,
            "FactionID": 0,
            "Flags": 0
        },
        {
            "Position": 0,
            "XPos": 1746,
            "YPos": -37,
            "ZPos": -1104,
            "TextureArchive": 1021,
            "TextureRecord": 5,
            "FactionID": 0,
            "Flags": 0
        },
        {
            "Position": 0,
            "XPos": 3148,
            "YPos": -2,
            "ZPos": -2857,
            "TextureArchive": 182,
            "TextureRecord": 30,
            "FactionID": 0,
            "Flags": 0
        },
        {
            "Position": 0,
            "XPos": 3075,
            "YPos": -2,
            "ZPos": -2864,
            "TextureArchive": 184,
            "TextureRecord": 27,
            "FactionID": 0,
            "Flags": 0
        },
        {
            "Position": 0,
            "XPos": 3036,
            "YPos": -2,
            "ZPos": -2687,
            "TextureArchive": 182,
            "TextureRecord": 29,
            "FactionID": 0,
            "Flags": 0
        },
        {
            "Position": 0,
            "XPos": 3267,
            "YPos": -1,
            "ZPos": -2894,
            "TextureArchive": 1025,
            "TextureRecord": 0,
            "FactionID": 0,
            "Flags": 0
        },
        {
            "Position": 0,
            "XPos": 3532,
            "YPos": -1,
            "ZPos": -2775,
            "TextureArchive": 1025,
            "TextureRecord": 3,
            "FactionID": 0,
            "Flags": 0
        },
        {
            "Position": 0,
            "XPos": 3278,
            "YPos": -1,
            "ZPos": -3051,
            "TextureArchive": 1025,
            "TextureRecord": 3,
            "FactionID": 0,
            "Flags": 0
        },
        {
            "Position": 0,
            "XPos": 3126,
            "YPos": -2,
            "ZPos": -2684,
            "TextureArchive": 1022,
            "TextureRecord": 3,
            "FactionID": 0,
            "Flags": 0
        },
        {
            "Position": 0,
            "XPos": 1440,
            "YPos": -2,
            "ZPos": -982,
            "TextureArchive": 97,
            "TextureRecord": 1,
            "FactionID": 0,
            "Flags": 0
        },
        {
            "Position": 0,
            "XPos": 3853,
            "YPos": -1,
            "ZPos": -2982,
            "TextureArchive": 1025,
            "TextureRecord": 0,
            "FactionID": 0,
            "Flags": 0
        },
        {
            "Position": 0,
            "XPos": 3270,
            "YPos": -1,
            "ZPos": -2663,
            "TextureArchive": 1025,
            "TextureRecord": 0,
            "FactionID": 0,
            "Flags": 0
        },
        {
            "Position": 0,
            "XPos": 2805,
            "YPos": -1,
            "ZPos": -2687,
            "TextureArchive": 204,
            "TextureRecord": 0,
            "FactionID": 0,
            "Flags": 0
        },
        {
            "Position": 0,
            "XPos": 3338,
            "YPos": -1,
            "ZPos": -2714,
            "TextureArchive": 205,
            "TextureRecord": 44,
            "FactionID": 0,
            "Flags": 0
        },
        {
            "Position": 0,
            "XPos": 3360,
            "YPos": -1,
            "ZPos": -2756,
            "TextureArchive": 200,
            "TextureRecord": 11,
            "FactionID": 0,
            "Flags": 0
        },
        {
            "Position": 0,
            "XPos": 3038,
            "YPos": -1,
            "ZPos": -2863,
            "TextureArchive": 200,
            "TextureRecord": 13,
            "FactionID": 0,
            "Flags": 0
        },
        {
            "Position": 0,
            "XPos": 2772,
            "YPos": -1,
            "ZPos": -2704,
            "TextureArchive": 200,
            "TextureRecord": 11,
            "FactionID": 0,
            "Flags": 0
        },
        {
            "Position": 0,
            "XPos": 2958,
            "YPos": -12,
            "ZPos": -2840,
            "TextureArchive": 205,
            "TextureRecord": 11,
            "FactionID": 0,
            "Flags": 0
        },
        {
            "Position": 0,
            "XPos": 3133,
            "YPos": -1,
            "ZPos": -2877,
            "TextureArchive": 205,
            "TextureRecord": 14,
            "FactionID": 0,
            "Flags": 0
        },
        {
            "Position": 0,
            "XPos": 3215,
            "YPos": -1,
            "ZPos": -2874,
            "TextureArchive": 205,
            "TextureRecord": 14,
            "FactionID": 0,
            "Flags": 0
        },
        {
            "Position": 0,
            "XPos": 3206,
            "YPos": -1,
            "ZPos": -2877,
            "TextureArchive": 205,
            "TextureRecord": 14,
            "FactionID": 0,
            "Flags": 0
        },
        {
            "Position": 0,
            "XPos": 3205,
            "YPos": -1,
            "ZPos": -2860,
            "TextureArchive": 205,
            "TextureRecord": 14,
            "FactionID": 0,
            "Flags": 0
        },
        {
            "Position": 0,
            "XPos": 3062,
            "YPos": -1,
            "ZPos": -2635,
            "TextureArchive": 205,
            "TextureRecord": 11,
            "FactionID": 0,
            "Flags": 0
        },
        {
            "Position": 0,
            "XPos": 3051,
            "YPos": -1,
            "ZPos": -2634,
            "TextureArchive": 205,
            "TextureRecord": 11,
            "FactionID": 0,
            "Flags": 0
        },
        {
            "Position": 0,
            "XPos": 2834,
            "YPos": -4,
            "ZPos": -2669,
            "TextureArchive": 211,
            "TextureRecord": 24,
            "FactionID": 0,
            "Flags": 0
        },
        {
            "Position": 0,
            "XPos": 1748,
            "YPos": -36,
            "ZPos": -1033,
            "TextureArchive": 1021,
            "TextureRecord": 1,
            "FactionID": 0,
            "Flags": 0
        },
        {
            "Position": 0,
            "XPos": 1662,
            "YPos": -2,
            "ZPos": -1284,
            "TextureArchive": 184,
            "TextureRecord": 33,
            "FactionID": 0,
            "Flags": 0
        },
        {
            "Position": 0,
            "XPos": 1791,
            "YPos": -35,
            "ZPos": -1370,
            "TextureArchive": 204,
            "TextureRecord": 3,
            "FactionID": 0,
            "Flags": 0
        },
        {
            "Position": 0,
            "XPos": 1721,
            "YPos": -37,
            "ZPos": -1372,
            "TextureArchive": 204,
            "TextureRecord": 5,
            "FactionID": 0,
            "Flags": 0
        },
        {
            "Position": 0,
            "XPos": 1719,
            "YPos": -4,
            "ZPos": -953,
            "TextureArchive": 1210,
            "TextureRecord": 8,
            "FactionID": 0,
            "Flags": 0
        },
        {
            "Position": 0,
            "XPos": 1764,
            "YPos": -4,
            "ZPos": -964,
            "TextureArchive": 1210,
            "TextureRecord": 9,
            "FactionID": 0,
            "Flags": 0
        },
        {
            "Position": 0,
            "XPos": 1713,
            "YPos": -34,
            "ZPos": -1300,
            "TextureArchive": 204,
            "TextureRecord": 6,
            "FactionID": 0,
            "Flags": 0
        },
        {
            "Position": 0,
            "XPos": 1691,
            "YPos": -3,
            "ZPos": -1139,
            "TextureArchive": 182,
            "TextureRecord": 25,
            "FactionID": 0,
            "Flags": 0
        },
        {
            "Position": 0,
            "XPos": 1791,
            "YPos": -37,
            "ZPos": -1032,
            "TextureArchive": 1021,
            "TextureRecord": 0,
            "FactionID": 0,
            "Flags": 0
        },
        {
            "Position": 0,
            "XPos": 1605,
            "YPos": -34,
            "ZPos": -1065,
            "TextureArchive": 211,
            "TextureRecord": 31,
            "FactionID": 0,
            "Flags": 0
        },
        {
            "Position": 0,
            "XPos": 1772,
            "YPos": -37,
            "ZPos": -1034,
            "TextureArchive": 1021,
            "TextureRecord": 0,
            "FactionID": 0,
            "Flags": 0
        },
        {
            "Position": 0,
            "XPos": 1605,
            "YPos": -34,
            "ZPos": -1031,
            "TextureArchive": 211,
            "TextureRecord": 31,
            "FactionID": 0,
            "Flags": 0
        }
    ]
}