{
    "Loaded": true,
    "Name": "Burning Omen of Arkay",
    "RegionName": "Ilessan Hills",
    "HasDungeon": false,
    "MapTableData": {
        "MapId": 185671253,
        "Latitude": 54568,
        "Longitude": 38568,
        "LocationType": "ReligionTemple",
        "DungeonType": "NoDungeon",
        "Discovered": true,
        "Key": 2
    },
    "Exterior": {
        "RecordElement": {
            "Header": {
                "X": 9877504,
                "Y": 13973505,
                "IsExterior": 32768,
                "Unknown2": 177,
                "LocationId": 14022,
                "IsInterior": 0,
                "ExteriorLocationId": 0,
                "LocationName": "Burning Omen of Arkay"
            }
        },
        "BuildingCount": 26,
        "Buildings": [
            {
                "NameSeed": 6491,
                "FactionId": 0,
                "Sector": 122,
                "LocationId": 14022,
                "BuildingType": "House5",
                "Quality": 10
            },
            {
                "NameSeed": 5597,
                "FactionId": 0,
                "Sector": 125,
                "LocationId": 14022,
                "BuildingType": "House5",
                "Quality": 10
            },
            {
                "NameSeed": 10814,
                "FactionId": 0,
                "Sector": 128,
                "LocationId": 14022,
                "BuildingType": "House5",
                "Quality": 0
            },
            {
                "NameSeed": 7581,
                "FactionId": 0,
                "Sector": 131,
                "LocationId": 14022,
                "BuildingType": "House5",
                "Quality": 0
            },
            {
                "NameSeed": 8663,
                "FactionId": 0,
                "Sector": 134,
                "LocationId": 14022,
                "BuildingType": "House5",
                "Quality": 0
            },
            {
                "NameSeed": 10122,
                "FactionId": 0,
                "Sector": 137,
                "LocationId": 14022,
                "BuildingType": "House5",
                "Quality": 10
            },
            {
                "NameSeed": 26087,
                "FactionId": 0,
                "Sector": 140,
                "LocationId": 14022,
                "BuildingType": "House5",
                "Quality": 0
            },
            {
                "NameSeed": 14393,
                "FactionId": 0,
                "Sector": 143,
                "LocationId": 14022,
                "BuildingType": "House5",
                "Quality": 5
            },
            {
                "NameSeed": 11635,
                "FactionId": 0,
                "Sector": 146,
                "LocationId": 14022,
                "BuildingType": "House5",
                "Quality": 5
            },
            {
                "NameSeed": 4491,
                "FactionId": 0,
                "Sector": 149,
                "LocationId": 14022,
                "BuildingType": "House5",
                "Quality": 0
            },
            {
                "NameSeed": 23257,
                "FactionId": 0,
                "Sector": 152,
                "LocationId": 14022,
                "BuildingType": "House5",
                "Quality": 0
            },
            {
                "NameSeed": 29227,
                "FactionId": 0,
                "Sector": 155,
                "LocationId": 14022,
                "BuildingType": "House5",
                "Quality": 0
            },
            {
                "NameSeed": 20783,
                "FactionId": 0,
                "Sector": 158,
                "LocationId": 14022,
                "BuildingType": "House5",
                "Quality": 0
            },
            {
                "NameSeed": 27203,
                "FactionId": 0,
                "Sector": 161,
                "LocationId": 14022,
                "BuildingType": "House5",
                "Quality": 0
            },
            {
                "NameSeed": 16834,
                "FactionId": 0,
                "Sector": 164,
                "LocationId": 14022,
                "BuildingType": "House5",
                "Quality": 0
            },
            {
                "NameSeed": 26076,
                "FactionId": 0,
                "Sector": 167,
                "LocationId": 14022,
                "BuildingType": "House5",
                "Quality": 0
            },
            {
                "NameSeed": 25733,
                "FactionId": 0,
                "Sector": 170,
                "LocationId": 14022,
                "BuildingType": "House5",
                "Quality": 0
            },
            {
                "NameSeed": 25170,
                "FactionId": 0,
                "Sector": 173,
                "LocationId": 14022,
                "BuildingType": "House5",
                "Quality": 0
            },
            {
                "NameSeed": 4329,
                "FactionId": 0,
                "Sector": 176,
                "LocationId": 14022,
                "BuildingType": "House5",
                "Quality": 0
            },
            {
                "NameSeed": 29556,
                "FactionId": 0,
                "Sector": 179,
                "LocationId": 14022,
                "BuildingType": "House5",
                "Quality": 0
            },
            {
                "NameSeed": 21033,
                "FactionId": 0,
                "Sector": 182,
                "LocationId": 14022,
                "BuildingType": "House5",
                "Quality": 0
            },
            {
                "NameSeed": 7208,
                "FactionId": 0,
                "Sector": 185,
                "LocationId": 14022,
                "BuildingType": "House5",
                "Quality": 0
            },
            {
                "NameSeed": 11844,
                "FactionId": 0,
                "Sector": 188,
                "LocationId": 14022,
                "BuildingType": "House5",
                "Quality": 0
            },
            {
                "NameSeed": 10618,
                "FactionId": 0,
                "Sector": 191,
                "LocationId": 14022,
                "BuildingType": "House5",
                "Quality": 0
            },
            {
                "NameSeed": 1548,
                "FactionId": 0,
                "Sector": 194,
                "LocationId": 14022,
                "BuildingType": "House5",
                "Quality": 0
            },
            {
                "NameSeed": 26625,
                "FactionId": 21,
                "Sector": 4,
                "LocationId": 14022,
                "BuildingType": "Temple",
                "Quality": 1
            }
        ],
        "ExteriorData": {
            "AnotherName": "Burning Omen of Arkay",
            "MapId": 73301,
            "LocationId": 0,
            "Width": 1,
            "Height": 1,
            "PortTownAndUnknown": 0,
            "BlockNames": [
                "TEMPASA2.RMB"
            ]
        }
    },
    "Dungeon": {
        "RecordElement": {
            "Header": {
                "X": 0,
                "Y": 0,
                "IsExterior": 0,
                "Unknown2": 0,
                "LocationId": 0,
                "IsInterior": 0,
                "ExteriorLocationId": 0,
                "LocationName": null
            }
        },
        "Header": {
            "BlockCount": 0
        },
        "Blocks": null
    },
    "Climate": {
        "WorldClimate": 231,
        "ClimateType": "Temperate",
        "NatureSet": "Nature_TemperateWoodland",
        "GroundArchive": 302,
        "NatureArchive": 504,
        "SkyBase": 16,
        "People": "Breton",
        "Names": "Nord"
    },
    "Politic": 188,
    "RegionIndex": 60,
    "LocationIndex": 177
}